{
"meta":{"test_sets":[],"test_metrics":[],"learn_metrics":[{"best_value":"Min","name":"Logloss"}],"launch_mode":"Train","parameters":"","iteration_count":1000,"learn_sets":["learn"],"name":"experiment"},
"iterations":[
{"learn":[0.689319025],"iteration":0,"passed_time":0.00503128004,"remaining_time":5.02624876},
{"learn":[0.686364605],"iteration":1,"passed_time":0.0112031775,"remaining_time":5.590385571},
{"learn":[0.6833056969],"iteration":2,"passed_time":0.01552624525,"remaining_time":5.159888839},
{"learn":[0.6805300737],"iteration":3,"passed_time":0.02003953229,"remaining_time":4.989843539},
{"learn":[0.6777128895],"iteration":4,"passed_time":0.02604668991,"remaining_time":5.183291293},
{"learn":[0.6744004147],"iteration":5,"passed_time":0.0304039888,"remaining_time":5.036927478},
{"learn":[0.6715018259],"iteration":6,"passed_time":0.0355722868,"remaining_time":5.04618297},
{"learn":[0.6680860425],"iteration":7,"passed_time":0.04112532033,"remaining_time":5.099539721},
{"learn":[0.6650084991],"iteration":8,"passed_time":0.04764641511,"remaining_time":5.246399708},
{"learn":[0.6612573299],"iteration":9,"passed_time":0.05202392897,"remaining_time":5.150368968},
{"learn":[0.6584358882],"iteration":10,"passed_time":0.05775332134,"remaining_time":5.192548619},
{"learn":[0.6557752142],"iteration":11,"passed_time":0.06427540773,"remaining_time":5.29200857},
{"learn":[0.6535031687],"iteration":12,"passed_time":0.07023820313,"remaining_time":5.332700499},
{"learn":[0.6509378765],"iteration":13,"passed_time":0.08036845087,"remaining_time":5.660235183},
{"learn":[0.6473392576],"iteration":14,"passed_time":0.08639302044,"remaining_time":5.673141676},
{"learn":[0.6451122006],"iteration":15,"passed_time":0.0942195639,"remaining_time":5.79450318},
{"learn":[0.6429367258],"iteration":16,"passed_time":0.09810957951,"remaining_time":5.673042156},
{"learn":[0.640338825],"iteration":17,"passed_time":0.1085900202,"remaining_time":5.92418888},
{"learn":[0.6376903609],"iteration":18,"passed_time":0.1166819594,"remaining_time":6.024473799},
{"learn":[0.635419135],"iteration":19,"passed_time":0.1293506868,"remaining_time":6.338183655},
{"learn":[0.6322064927],"iteration":20,"passed_time":0.1352713574,"remaining_time":6.306221853},
{"learn":[0.6289976918],"iteration":21,"passed_time":0.1465914193,"remaining_time":6.516654912},
{"learn":[0.6268524996],"iteration":22,"passed_time":0.1640555221,"remaining_time":6.968793265},
{"learn":[0.6242782324],"iteration":23,"passed_time":0.17898045,"remaining_time":7.2785383},
{"learn":[0.6216085748],"iteration":24,"passed_time":0.1891275631,"remaining_time":7.375974962},
{"learn":[0.6195614946],"iteration":25,"passed_time":0.2105015319,"remaining_time":7.885711232},
{"learn":[0.6171273519],"iteration":26,"passed_time":0.2236901551,"remaining_time":8.061130406},
{"learn":[0.6151766274],"iteration":27,"passed_time":0.234227646,"remaining_time":8.131045427},
{"learn":[0.6130275717],"iteration":28,"passed_time":0.2452735042,"remaining_time":8.212433538},
{"learn":[0.6106206059],"iteration":29,"passed_time":0.2583153462,"remaining_time":8.352196192},
{"learn":[0.6084461862],"iteration":30,"passed_time":0.2732032288,"remaining_time":8.539804153},
{"learn":[0.6067117747],"iteration":31,"passed_time":0.2800538766,"remaining_time":8.471629768},
{"learn":[0.6042640484],"iteration":32,"passed_time":0.2900591032,"remaining_time":8.49961069},
{"learn":[0.6025283481],"iteration":33,"passed_time":0.2936122568,"remaining_time":8.342042355},
{"learn":[0.6007138356],"iteration":34,"passed_time":0.3040340328,"remaining_time":8.382652618},
{"learn":[0.5984837279],"iteration":35,"passed_time":0.3098940424,"remaining_time":8.298273801},
{"learn":[0.5962866224],"iteration":36,"passed_time":0.3197368067,"remaining_time":8.321798509},
{"learn":[0.5936163338],"iteration":37,"passed_time":0.3256120209,"remaining_time":8.243125372},
{"learn":[0.5913790536],"iteration":38,"passed_time":0.3363182854,"remaining_time":8.287227494},
{"learn":[0.5897318682],"iteration":39,"passed_time":0.3416148015,"remaining_time":8.198755235},
{"learn":[0.5879808184],"iteration":40,"passed_time":0.3502667611,"remaining_time":8.192824972},
{"learn":[0.5856738363],"iteration":41,"passed_time":0.3556690729,"remaining_time":8.112642187},
{"learn":[0.5838113506],"iteration":42,"passed_time":0.3635306472,"remaining_time":8.090670451},
{"learn":[0.5817184538],"iteration":43,"passed_time":0.3698414554,"remaining_time":8.035646168},
{"learn":[0.5793443006],"iteration":44,"passed_time":0.3740142235,"remaining_time":7.937412965},
{"learn":[0.5771460589],"iteration":45,"passed_time":0.3820339249,"remaining_time":7.923051399},
{"learn":[0.5749566888],"iteration":46,"passed_time":0.3861766493,"remaining_time":7.830347803},
{"learn":[0.5726600054],"iteration":47,"passed_time":0.3902915443,"remaining_time":7.740782295},
{"learn":[0.5703594206],"iteration":48,"passed_time":0.3997035903,"remaining_time":7.757512538},
{"learn":[0.5687464953],"iteration":49,"passed_time":0.4054316575,"remaining_time":7.703201493},
{"learn":[0.5667169535],"iteration":50,"passed_time":0.4137865732,"remaining_time":7.699675647},
{"learn":[0.5650502477],"iteration":51,"passed_time":0.4183216917,"remaining_time":7.626326226},
{"learn":[0.5632754125],"iteration":52,"passed_time":0.4226667748,"remaining_time":7.552178034},
{"learn":[0.5617950982],"iteration":53,"passed_time":0.4297165724,"remaining_time":7.527997732},
{"learn":[0.5598934121],"iteration":54,"passed_time":0.4341479828,"remaining_time":7.459451705},
{"learn":[0.5577780875],"iteration":55,"passed_time":0.4385210038,"remaining_time":7.392211207},
{"learn":[0.5557468012],"iteration":56,"passed_time":0.4459289172,"remaining_time":7.377385419},
{"learn":[0.5537250692],"iteration":57,"passed_time":0.4501646138,"remaining_time":7.311294244},
{"learn":[0.5514895351],"iteration":58,"passed_time":0.4542852414,"remaining_time":7.245464613},
{"learn":[0.549123148],"iteration":59,"passed_time":0.4615191228,"remaining_time":7.230466256},
{"learn":[0.5470104033],"iteration":60,"passed_time":0.4655402338,"remaining_time":7.166266878},
{"learn":[0.5454227209],"iteration":61,"passed_time":0.4696693248,"remaining_time":7.105642366},
{"learn":[0.5438094772],"iteration":62,"passed_time":0.4768789253,"remaining_time":7.092627825},
{"learn":[0.5421381771],"iteration":63,"passed_time":0.4845987034,"remaining_time":7.087256037},
{"learn":[0.5402651379],"iteration":64,"passed_time":0.4909763654,"remaining_time":7.062506179},
{"learn":[0.5384985489],"iteration":65,"passed_time":0.4956069196,"remaining_time":7.013588831},
{"learn":[0.5364457132],"iteration":66,"passed_time":0.5009957206,"remaining_time":6.976552348},
{"learn":[0.5342391917],"iteration":67,"passed_time":0.506489571,"remaining_time":6.941886473},
{"learn":[0.5319386904],"iteration":68,"passed_time":0.5108861214,"remaining_time":6.893260565},
{"learn":[0.5301853971],"iteration":69,"passed_time":0.51519065,"remaining_time":6.844675778},
{"learn":[0.5289134845],"iteration":70,"passed_time":0.5193735973,"remaining_time":6.795747492},
{"learn":[0.5273527657],"iteration":71,"passed_time":0.525319663,"remaining_time":6.770786767},
{"learn":[0.5252512355],"iteration":72,"passed_time":0.5297037433,"remaining_time":6.726511919},
{"learn":[0.5238486917],"iteration":73,"passed_time":0.5339584825,"remaining_time":6.681696686},
{"learn":[0.5219218905],"iteration":74,"passed_time":0.5399033465,"remaining_time":6.65880794},
{"learn":[0.5203912085],"iteration":75,"passed_time":0.5444799911,"remaining_time":6.619730418},
{"learn":[0.5186851415],"iteration":76,"passed_time":0.5487507366,"remaining_time":6.577882206},
{"learn":[0.5169533781],"iteration":77,"passed_time":0.5550272524,"remaining_time":6.560706753},
{"learn":[0.5155998814],"iteration":78,"passed_time":0.559123999,"remaining_time":6.518394976},
{"learn":[0.5136299647],"iteration":79,"passed_time":0.5633718883,"remaining_time":6.478776716},
{"learn":[0.5120335572],"iteration":80,"passed_time":0.5675271289,"remaining_time":6.438980635},
{"learn":[0.5102630027],"iteration":81,"passed_time":0.5749989634,"remaining_time":6.437183517},
{"learn":[0.5088647942],"iteration":82,"passed_time":0.5796908437,"remaining_time":6.404536188},
{"learn":[0.5075039266],"iteration":83,"passed_time":0.5853535048,"remaining_time":6.3831406},
{"learn":[0.5059048786],"iteration":84,"passed_time":0.5901811361,"remaining_time":6.353126348},
{"learn":[0.5043601031],"iteration":85,"passed_time":0.5946077482,"remaining_time":6.319435836},
{"learn":[0.5029233685],"iteration":86,"passed_time":0.5988957781,"remaining_time":6.284963741},
{"learn":[0.5019246694],"iteration":87,"passed_time":0.6056765651,"remaining_time":6.277011675},
{"learn":[0.5005187249],"iteration":88,"passed_time":0.6100408736,"remaining_time":6.244350965},
{"learn":[0.4992265197],"iteration":89,"passed_time":0.6142847402,"remaining_time":6.211101262},
{"learn":[0.4978104328],"iteration":90,"passed_time":0.6209214735,"remaining_time":6.202391422},
{"learn":[0.4962680916],"iteration":91,"passed_time":0.6255552678,"remaining_time":6.173958512},
{"learn":[0.4948138394],"iteration":92,"passed_time":0.6297924051,"remaining_time":6.14216894},
{"learn":[0.4933715101],"iteration":93,"passed_time":0.6354723295,"remaining_time":6.124871601},
{"learn":[0.4920102722],"iteration":94,"passed_time":0.639786736,"remaining_time":6.094810485},
{"learn":[0.4903972154],"iteration":95,"passed_time":0.6440296963,"remaining_time":6.064612974},
{"learn":[0.4892173217],"iteration":96,"passed_time":0.6484710429,"remaining_time":6.036797441},
{"learn":[0.4877160435],"iteration":97,"passed_time":0.6542467868,"remaining_time":6.021740833},
{"learn":[0.485528207],"iteration":98,"passed_time":0.6583932787,"remaining_time":5.99204388},
{"learn":[0.4845229777],"iteration":99,"passed_time":0.6623647168,"remaining_time":5.961282451},
{"learn":[0.4833788224],"iteration":100,"passed_time":0.6690237327,"remaining_time":5.954973621},
{"learn":[0.4822253587],"iteration":101,"passed_time":0.6741319414,"remaining_time":5.935004739},
{"learn":[0.4809746308],"iteration":102,"passed_time":0.6783640794,"remaining_time":5.907694944},
{"learn":[0.479424822],"iteration":103,"passed_time":0.6845722224,"remaining_time":5.897852993},
{"learn":[0.4780120143],"iteration":104,"passed_time":0.6889201879,"remaining_time":5.872224459},
{"learn":[0.4767503877],"iteration":105,"passed_time":0.6931445116,"remaining_time":5.845954655},
{"learn":[0.4756383292],"iteration":106,"passed_time":0.699177209,"remaining_time":5.83518923},
{"learn":[0.4739851849],"iteration":107,"passed_time":0.7039568572,"remaining_time":5.814162191},
{"learn":[0.4726677048],"iteration":108,"passed_time":0.708111481,"remaining_time":5.788324124},
{"learn":[0.4712520276],"iteration":109,"passed_time":0.7137895116,"remaining_time":5.775206048},
{"learn":[0.4701749287],"iteration":110,"passed_time":0.7181631102,"remaining_time":5.75177482},
{"learn":[0.468787634],"iteration":111,"passed_time":0.7225159012,"remaining_time":5.728518931},
{"learn":[0.4673214327],"iteration":112,"passed_time":0.726653982,"remaining_time":5.70391223},
{"learn":[0.4662335497],"iteration":113,"passed_time":0.7344422897,"remaining_time":5.708033935},
{"learn":[0.4648401304],"iteration":114,"passed_time":0.7387560371,"remaining_time":5.685209503},
{"learn":[0.4639889362],"iteration":115,"passed_time":0.7429567149,"remaining_time":5.661842551},
{"learn":[0.4628265664],"iteration":116,"passed_time":0.7492504648,"remaining_time":5.654599662},
{"learn":[0.4621509466],"iteration":117,"passed_time":0.7536186071,"remaining_time":5.632979758},
{"learn":[0.4615472727],"iteration":118,"passed_time":0.7571121195,"remaining_time":5.605174599},
{"learn":[0.4605104838],"iteration":119,"passed_time":0.7635994523,"remaining_time":5.599729317},
{"learn":[0.4591998678],"iteration":120,"passed_time":0.7677651495,"remaining_time":5.577401375},
{"learn":[0.4587279758],"iteration":121,"passed_time":0.7699885535,"remaining_time":5.541393032},
{"learn":[0.4575195387],"iteration":122,"passed_time":0.7741697889,"remaining_time":5.519893535},
{"learn":[0.4566277931],"iteration":123,"passed_time":0.7805549588,"remaining_time":5.514243096},
{"learn":[0.4557060922],"iteration":124,"passed_time":0.7858813427,"remaining_time":5.501169399},
{"learn":[0.4549145355],"iteration":125,"passed_time":0.790019092,"remaining_time":5.479973701},
{"learn":[0.4533225324],"iteration":126,"passed_time":0.7960967845,"remaining_time":5.472381834},
{"learn":[0.4518791269],"iteration":127,"passed_time":0.8008243366,"remaining_time":5.455615793},
{"learn":[0.4509035023],"iteration":128,"passed_time":0.8050601919,"remaining_time":5.43571649},
{"learn":[0.4497546101],"iteration":129,"passed_time":0.8105571799,"remaining_time":5.42449805},
{"learn":[0.4484917831],"iteration":130,"passed_time":0.8147240465,"remaining_time":5.404543484},
{"learn":[0.4476194728],"iteration":131,"passed_time":0.818955202,"remaining_time":5.385250874},
{"learn":[0.4461050725],"iteration":132,"passed_time":0.8229541962,"remaining_time":5.364671339},
{"learn":[0.4453087576],"iteration":133,"passed_time":0.8292821813,"remaining_time":5.359390813},
{"learn":[0.4441452568],"iteration":134,"passed_time":0.8341515165,"remaining_time":5.344748606},
{"learn":[0.4433256818],"iteration":135,"passed_time":0.8385879422,"remaining_time":5.327499868},
{"learn":[0.4421696605],"iteration":136,"passed_time":0.8449831217,"remaining_time":5.32277689},
{"learn":[0.4410975416],"iteration":137,"passed_time":0.8492670806,"remaining_time":5.304842199},
{"learn":[0.439934063],"iteration":138,"passed_time":0.8535381798,"remaining_time":5.287024265},
{"learn":[0.4387703341],"iteration":139,"passed_time":0.8614386268,"remaining_time":5.291694422},
{"learn":[0.437618527],"iteration":140,"passed_time":0.8663728587,"remaining_time":5.278115501},
{"learn":[0.4369552695],"iteration":141,"passed_time":0.8715112155,"remaining_time":5.26589171},
{"learn":[0.4356988832],"iteration":142,"passed_time":0.8834358117,"remaining_time":5.294436997},
{"learn":[0.4346507717],"iteration":143,"passed_time":0.8876159419,"remaining_time":5.276383655},
{"learn":[0.4334953277],"iteration":144,"passed_time":0.8940741644,"remaining_time":5.271954556},
{"learn":[0.4331513282],"iteration":145,"passed_time":0.8965888967,"remaining_time":5.244430944},
{"learn":[0.4320755414],"iteration":146,"passed_time":0.9009416716,"remaining_time":5.227913237},
{"learn":[0.4310825759],"iteration":147,"passed_time":0.9063258984,"remaining_time":5.217497739},
{"learn":[0.4301935426],"iteration":148,"passed_time":0.9107188902,"remaining_time":5.201488427},
{"learn":[0.4287408774],"iteration":149,"passed_time":0.915066051,"remaining_time":5.185374289},
{"learn":[0.4274115883],"iteration":150,"passed_time":0.9191670072,"remaining_time":5.168031716},
{"learn":[0.4263362664],"iteration":151,"passed_time":0.925066864,"remaining_time":5.160899346},
{"learn":[0.4250578042],"iteration":152,"passed_time":0.9292772168,"remaining_time":5.144430082},
{"learn":[0.4238603571],"iteration":153,"passed_time":0.9336342293,"remaining_time":5.128925701},
{"learn":[0.4223752726],"iteration":154,"passed_time":0.9393456351,"remaining_time":5.120948785},
{"learn":[0.4213999014],"iteration":155,"passed_time":0.9439029016,"remaining_time":5.106756724},
{"learn":[0.4202463802],"iteration":156,"passed_time":0.9481284028,"remaining_time":5.09090601},
{"learn":[0.4191742696],"iteration":157,"passed_time":0.9526958445,"remaining_time":5.077024691},
{"learn":[0.4185297005],"iteration":158,"passed_time":0.9573800783,"remaining_time":5.063878276},
{"learn":[0.4178703605],"iteration":159,"passed_time":0.9616806404,"remaining_time":5.048823362},
{"learn":[0.4168416971],"iteration":160,"passed_time":0.9658208893,"remaining_time":5.033066622},
{"learn":[0.41605227],"iteration":161,"passed_time":0.9717030287,"remaining_time":5.026463815},
{"learn":[0.4151332852],"iteration":162,"passed_time":0.9769341267,"remaining_time":5.016526773},
{"learn":[0.4145438378],"iteration":163,"passed_time":0.9812291691,"remaining_time":5.001875521},
{"learn":[0.4136711565],"iteration":164,"passed_time":0.9871096639,"remaining_time":4.995373148},
{"learn":[0.4124918446],"iteration":165,"passed_time":0.9916306056,"remaining_time":4.982047741},
{"learn":[0.4114479143],"iteration":166,"passed_time":0.9956466511,"remaining_time":4.966309343},
{"learn":[0.4105904982],"iteration":167,"passed_time":0.9998042988,"remaining_time":4.951411766},
{"learn":[0.4097344649],"iteration":168,"passed_time":1.005824343,"remaining_time":4.94579899},
{"learn":[0.4089368545],"iteration":169,"passed_time":1.010043829,"remaining_time":4.931390457},
{"learn":[0.408535075],"iteration":170,"passed_time":1.014179418,"remaining_time":4.916694371},
{"learn":[0.4077277353],"iteration":171,"passed_time":1.019993315,"remaining_time":4.910200377},
{"learn":[0.4069108221],"iteration":172,"passed_time":1.025184471,"remaining_time":4.900737328},
{"learn":[0.4056110576],"iteration":173,"passed_time":1.029477591,"remaining_time":4.887060287},
{"learn":[0.4046718314],"iteration":174,"passed_time":1.035416344,"remaining_time":4.881248481},
{"learn":[0.403635232],"iteration":175,"passed_time":1.039799332,"remaining_time":4.868151417},
{"learn":[0.4028454326],"iteration":176,"passed_time":1.04413347,"remaining_time":4.854925682},
{"learn":[0.4019443957],"iteration":177,"passed_time":1.048525578,"remaining_time":4.842067555},
{"learn":[0.4009154827],"iteration":178,"passed_time":1.053180392,"remaining_time":4.830508947},
{"learn":[0.4004654245],"iteration":179,"passed_time":1.057537051,"remaining_time":4.817668786},
{"learn":[0.3995398718],"iteration":180,"passed_time":1.061947017,"remaining_time":4.805163575},
{"learn":[0.3986571197],"iteration":181,"passed_time":1.068370963,"remaining_time":4.801799165},
{"learn":[0.3974032029],"iteration":182,"passed_time":1.072403104,"remaining_time":4.787723146},
{"learn":[0.3964473278],"iteration":183,"passed_time":1.077538991,"remaining_time":4.778651178},
{"learn":[0.3958801454],"iteration":184,"passed_time":1.084486028,"remaining_time":4.77760061},
{"learn":[0.394972696],"iteration":185,"passed_time":1.089689001,"remaining_time":4.768854016},
{"learn":[0.3942401116],"iteration":186,"passed_time":1.094323592,"remaining_time":4.757674227},
{"learn":[0.3936509438],"iteration":187,"passed_time":1.100925805,"remaining_time":4.755062519},
{"learn":[0.3928314474],"iteration":188,"passed_time":1.105278122,"remaining_time":4.742754268},
{"learn":[0.3920690071],"iteration":189,"passed_time":1.109481156,"remaining_time":4.729893351},
{"learn":[0.3912375435],"iteration":190,"passed_time":1.115610179,"remaining_time":4.725280809},
{"learn":[0.3903907132],"iteration":191,"passed_time":1.120785075,"remaining_time":4.716637192},
{"learn":[0.3897383906],"iteration":192,"passed_time":1.125627036,"remaining_time":4.7066374},
{"learn":[0.3888694239],"iteration":193,"passed_time":1.134822508,"remaining_time":4.71477805},
{"learn":[0.3880108908],"iteration":194,"passed_time":1.140862851,"remaining_time":4.709715873},
{"learn":[0.3868934517],"iteration":195,"passed_time":1.147913909,"remaining_time":4.708789707},
{"learn":[0.3866090599],"iteration":196,"passed_time":1.151299575,"remaining_time":4.692860703},
{"learn":[0.3860366216],"iteration":197,"passed_time":1.156856325,"remaining_time":4.685852385},
{"learn":[0.38539079],"iteration":198,"passed_time":1.16328978,"remaining_time":4.682387506},
{"learn":[0.3841924027],"iteration":199,"passed_time":1.167708976,"remaining_time":4.670835902},
{"learn":[0.3835834914],"iteration":200,"passed_time":1.172085237,"remaining_time":4.659184597},
{"learn":[0.3829562308],"iteration":201,"passed_time":1.177907007,"remaining_time":4.653315802},
{"learn":[0.3823043968],"iteration":202,"passed_time":1.184416926,"remaining_time":4.650149213},
{"learn":[0.3817269819],"iteration":203,"passed_time":1.189201668,"remaining_time":4.640218274},
{"learn":[0.38109692],"iteration":204,"passed_time":1.195792086,"remaining_time":4.637340042},
{"learn":[0.3805879435],"iteration":205,"passed_time":1.202054474,"remaining_time":4.633161421},
{"learn":[0.3800480054],"iteration":206,"passed_time":1.214623943,"remaining_time":4.653124575},
{"learn":[0.3791513451],"iteration":207,"passed_time":1.223886568,"remaining_time":4.66018347},
{"learn":[0.3786503155],"iteration":208,"passed_time":1.23820755,"remaining_time":4.686230489},
{"learn":[0.377806358],"iteration":209,"passed_time":1.254137676,"remaining_time":4.717946495},
{"learn":[0.3770598382],"iteration":210,"passed_time":1.266672042,"remaining_time":4.73651299},
{"learn":[0.3760252735],"iteration":211,"passed_time":1.272498788,"remaining_time":4.729853984},
{"learn":[0.3754067003],"iteration":212,"passed_time":1.289343726,"remaining_time":4.763913204},
{"learn":[0.3746560148],"iteration":213,"passed_time":1.303159288,"remaining_time":4.786370095},
{"learn":[0.374014167],"iteration":214,"passed_time":1.315470045,"remaining_time":4.802995281},
{"learn":[0.373621751],"iteration":215,"passed_time":1.321127464,"remaining_time":4.795203388},
{"learn":[0.3726079363],"iteration":216,"passed_time":1.333007512,"remaining_time":4.809884249},
{"learn":[0.3718048328],"iteration":217,"passed_time":1.338332822,"remaining_time":4.800808563},
{"learn":[0.3712396361],"iteration":218,"passed_time":1.352002061,"remaining_time":4.82152333},
{"learn":[0.3706586822],"iteration":219,"passed_time":1.36364495,"remaining_time":4.834741187},
{"learn":[0.3701107471],"iteration":220,"passed_time":1.369607132,"remaining_time":4.827710206},
{"learn":[0.3692550045],"iteration":221,"passed_time":1.382523544,"remaining_time":4.845059986},
{"learn":[0.3686978764],"iteration":222,"passed_time":1.389501984,"remaining_time":4.841448618},
{"learn":[0.3679748046],"iteration":223,"passed_time":1.399414323,"remaining_time":4.847971048},
{"learn":[0.3676863341],"iteration":224,"passed_time":1.409260288,"remaining_time":4.854118771},
{"learn":[0.3668615389],"iteration":225,"passed_time":1.416717906,"remaining_time":4.851945394},
{"learn":[0.3663072752],"iteration":226,"passed_time":1.430422096,"remaining_time":4.870996828},
{"learn":[0.3656854597],"iteration":227,"passed_time":1.441044957,"remaining_time":4.87932766},
{"learn":[0.3651605558],"iteration":228,"passed_time":1.447620577,"remaining_time":4.873866658},
{"learn":[0.3644641057],"iteration":229,"passed_time":1.459935132,"remaining_time":4.887608919},
{"learn":[0.3638276683],"iteration":230,"passed_time":1.465754861,"remaining_time":4.879504278},
{"learn":[0.3632397661],"iteration":231,"passed_time":1.476235336,"remaining_time":4.886848009},
{"learn":[0.3624163798],"iteration":232,"passed_time":1.481118755,"remaining_time":4.875614098},
{"learn":[0.3617729885],"iteration":233,"passed_time":1.490778403,"remaining_time":4.880069472},
{"learn":[0.3609976251],"iteration":234,"passed_time":1.496500351,"remaining_time":4.871586251},
{"learn":[0.360052319],"iteration":235,"passed_time":1.504122024,"remaining_time":4.869276381},
{"learn":[0.3598996401],"iteration":236,"passed_time":1.509171001,"remaining_time":4.858639129},
{"learn":[0.3591140482],"iteration":237,"passed_time":1.515674271,"remaining_time":4.852705018},
{"learn":[0.3588511409],"iteration":238,"passed_time":1.525440566,"remaining_time":4.857155943},
{"learn":[0.358225205],"iteration":239,"passed_time":1.534548127,"remaining_time":4.859402403},
{"learn":[0.357660221],"iteration":240,"passed_time":1.541512357,"remaining_time":4.854804477},
{"learn":[0.3570870682],"iteration":241,"passed_time":1.545879245,"remaining_time":4.842051521},
{"learn":[0.3567542422],"iteration":242,"passed_time":1.554698319,"remaining_time":4.84323715},
{"learn":[0.3560266052],"iteration":243,"passed_time":1.558895452,"remaining_time":4.830020335},
{"learn":[0.3557343131],"iteration":244,"passed_time":1.56493163,"remaining_time":4.82254441},
{"learn":[0.3550854959],"iteration":245,"passed_time":1.572337848,"remaining_time":4.819279421},
{"learn":[0.3544512969],"iteration":246,"passed_time":1.577912031,"remaining_time":4.810395787},
{"learn":[0.3535333987],"iteration":247,"passed_time":1.5885268,"remaining_time":4.816823201},
{"learn":[0.3528584807],"iteration":248,"passed_time":1.59298427,"remaining_time":4.804542918},
{"learn":[0.3522524694],"iteration":249,"passed_time":1.601450513,"remaining_time":4.804351539},
{"learn":[0.3516121099],"iteration":250,"passed_time":1.605804433,"remaining_time":4.791822791},
{"learn":[0.351036551],"iteration":251,"passed_time":1.610093632,"remaining_time":4.779166814},
{"learn":[0.3501941144],"iteration":252,"passed_time":1.617929101,"remaining_time":4.777047584},
{"learn":[0.3493416344],"iteration":253,"passed_time":1.622223712,"remaining_time":4.764483815},
{"learn":[0.3488553146],"iteration":254,"passed_time":1.626414805,"remaining_time":4.75168247},
{"learn":[0.3479548639],"iteration":255,"passed_time":1.633535015,"remaining_time":4.747461137},
{"learn":[0.347358626],"iteration":256,"passed_time":1.638022777,"remaining_time":4.735606707},
{"learn":[0.3467044961],"iteration":257,"passed_time":1.642353423,"remaining_time":4.72335752},
{"learn":[0.3459502077],"iteration":258,"passed_time":1.648745765,"remaining_time":4.717067998},
{"learn":[0.3451760937],"iteration":259,"passed_time":1.652960566,"remaining_time":4.704580073},
{"learn":[0.3445647388],"iteration":260,"passed_time":1.657072612,"remaining_time":4.691864598},
{"learn":[0.3441107782],"iteration":261,"passed_time":1.663510125,"remaining_time":4.685765161},
{"learn":[0.3434718149],"iteration":262,"passed_time":1.667922951,"remaining_time":4.67398941},
{"learn":[0.3430604433],"iteration":263,"passed_time":1.672224192,"remaining_time":4.661958355},
{"learn":[0.342207667],"iteration":264,"passed_time":1.680372017,"remaining_time":4.660654463},
{"learn":[0.3413404138],"iteration":265,"passed_time":1.686688599,"remaining_time":4.654245985},
{"learn":[0.3404984889],"iteration":266,"passed_time":1.690820465,"remaining_time":4.641840454},
{"learn":[0.3399988871],"iteration":267,"passed_time":1.697322429,"remaining_time":4.635970217},
{"learn":[0.3393237096],"iteration":268,"passed_time":1.701831101,"remaining_time":4.624678568},
{"learn":[0.3387759126],"iteration":269,"passed_time":1.705880049,"remaining_time":4.612194207},
{"learn":[0.338085638],"iteration":270,"passed_time":1.712118038,"remaining_time":4.6056607},
{"learn":[0.3377235143],"iteration":271,"passed_time":1.716552231,"remaining_time":4.59430156},
{"learn":[0.3372066431],"iteration":272,"passed_time":1.720733776,"remaining_time":4.582320349},
{"learn":[0.3361912863],"iteration":273,"passed_time":1.726223564,"remaining_time":4.573862435},
{"learn":[0.3357352882],"iteration":274,"passed_time":1.730568332,"remaining_time":4.562407421},
{"learn":[0.3353819412],"iteration":275,"passed_time":1.734728958,"remaining_time":4.55052089},
{"learn":[0.3346795963],"iteration":276,"passed_time":1.739045121,"remaining_time":4.539096109},
{"learn":[0.3339995182],"iteration":277,"passed_time":1.744892694,"remaining_time":4.531699731},
{"learn":[0.3336097673],"iteration":278,"passed_time":1.749083775,"remaining_time":4.520033699},
{"learn":[0.3331827988],"iteration":279,"passed_time":1.753325578,"remaining_time":4.508551487},
{"learn":[0.3321232765],"iteration":280,"passed_time":1.759422626,"remaining_time":4.501867858},
{"learn":[0.3313693714],"iteration":281,"passed_time":1.763587325,"remaining_time":4.490268436},
{"learn":[0.3308008627],"iteration":282,"passed_time":1.767776406,"remaining_time":4.478783334},
{"learn":[0.3301970933],"iteration":283,"passed_time":1.774302889,"remaining_time":4.473242495},
{"learn":[0.3293678539],"iteration":284,"passed_time":1.778502629,"remaining_time":4.461857472},
{"learn":[0.3283115108],"iteration":285,"passed_time":1.782794655,"remaining_time":4.45075309},
{"learn":[0.3277865978],"iteration":286,"passed_time":1.786939899,"remaining_time":4.439331527},
{"learn":[0.3271507638],"iteration":287,"passed_time":1.793599814,"remaining_time":4.434177319},
{"learn":[0.3268480791],"iteration":288,"passed_time":1.798451376,"remaining_time":4.424563766},
{"learn":[0.3263664633],"iteration":289,"passed_time":1.802680506,"remaining_time":4.41345917},
{"learn":[0.3260623569],"iteration":290,"passed_time":1.808884282,"remaining_time":4.407212906},
{"learn":[0.3256419142],"iteration":291,"passed_time":1.813391273,"remaining_time":4.396852814},
{"learn":[0.3249286107],"iteration":292,"passed_time":1.817547689,"remaining_time":4.385686745},
{"learn":[0.3243857965],"iteration":293,"passed_time":1.823566181,"remaining_time":4.379039876},
{"learn":[0.3240844535],"iteration":294,"passed_time":1.828720252,"remaining_time":4.370331449},
{"learn":[0.3238310191],"iteration":295,"passed_time":1.833012732,"remaining_time":4.359597849},
{"learn":[0.3233774128],"iteration":296,"passed_time":1.838285547,"remaining_time":4.351228079},
{"learn":[0.3227899161],"iteration":297,"passed_time":1.842955295,"remaining_time":4.341458448},
{"learn":[0.322271189],"iteration":298,"passed_time":1.847231814,"remaining_time":4.330801008},
{"learn":[0.3215417734],"iteration":299,"passed_time":1.8515263,"remaining_time":4.320228033},
{"learn":[0.3208362015],"iteration":300,"passed_time":1.857762863,"remaining_time":4.314206781},
{"learn":[0.3203397582],"iteration":301,"passed_time":1.86200349,"remaining_time":4.303570981},
{"learn":[0.319562627],"iteration":302,"passed_time":1.866060096,"remaining_time":4.292554083},
{"learn":[0.3189393169],"iteration":303,"passed_time":1.872771269,"remaining_time":4.287660536},
{"learn":[0.3185544511],"iteration":304,"passed_time":1.876939776,"remaining_time":4.276961129},
{"learn":[0.3178757689],"iteration":305,"passed_time":1.881391713,"remaining_time":4.266947218},
{"learn":[0.3171494033],"iteration":306,"passed_time":1.88739984,"remaining_time":4.260482375},
{"learn":[0.3164289492],"iteration":307,"passed_time":1.892943948,"remaining_time":4.252977961},
{"learn":[0.3158328559],"iteration":308,"passed_time":1.897562008,"remaining_time":4.243415364},
{"learn":[0.3153288294],"iteration":309,"passed_time":1.903864919,"remaining_time":4.237634819},
{"learn":[0.3147037286],"iteration":310,"passed_time":1.908258641,"remaining_time":4.227621233},
{"learn":[0.3142313156],"iteration":311,"passed_time":1.912538515,"remaining_time":4.217392622},
{"learn":[0.3136890853],"iteration":312,"passed_time":1.918611049,"remaining_time":4.211136712},
{"learn":[0.3133057382],"iteration":313,"passed_time":1.922960048,"remaining_time":4.201116537},
{"learn":[0.3129777337],"iteration":314,"passed_time":1.927244973,"remaining_time":4.190993037},
{"learn":[0.312440385],"iteration":315,"passed_time":1.931701224,"remaining_time":4.181277333},
{"learn":[0.3121105036],"iteration":316,"passed_time":1.937321624,"remaining_time":4.174103056},
{"learn":[0.3115819045],"iteration":317,"passed_time":1.94176025,"remaining_time":4.164404057},
{"learn":[0.3113391763],"iteration":318,"passed_time":1.946943835,"remaining_time":4.156328374},
{"learn":[0.3107640535],"iteration":319,"passed_time":1.956350513,"remaining_time":4.157244839},
{"learn":[0.3102145204],"iteration":320,"passed_time":1.961061938,"remaining_time":4.148165283},
{"learn":[0.309807448],"iteration":321,"passed_time":1.968162646,"remaining_time":4.144143708},
{"learn":[0.3093783718],"iteration":322,"passed_time":1.973838289,"remaining_time":4.137116165},
{"learn":[0.308900439],"iteration":323,"passed_time":1.983567314,"remaining_time":4.138554026},
{"learn":[0.308424493],"iteration":324,"passed_time":1.994098419,"remaining_time":4.141589025},
{"learn":[0.3077466335],"iteration":325,"passed_time":2.003372008,"remaining_time":4.141940899},
{"learn":[0.3071168732],"iteration":326,"passed_time":2.009360416,"remaining_time":4.135472661},
{"learn":[0.3065317027],"iteration":327,"passed_time":2.020922649,"remaining_time":4.14042689},
{"learn":[0.3058444337],"iteration":328,"passed_time":2.026791713,"remaining_time":4.133669422},
{"learn":[0.3053786878],"iteration":329,"passed_time":2.038525349,"remaining_time":4.138824193},
{"learn":[0.3049561645],"iteration":330,"passed_time":2.044209432,"remaining_time":4.131649879},
{"learn":[0.3045822261],"iteration":331,"passed_time":2.055903445,"remaining_time":4.136576811},
{"learn":[0.3040453256],"iteration":332,"passed_time":2.064040731,"remaining_time":4.134279782},
{"learn":[0.303481082],"iteration":333,"passed_time":2.072652859,"remaining_time":4.132894624},
{"learn":[0.3031576992],"iteration":334,"passed_time":2.077145796,"remaining_time":4.123289416},
{"learn":[0.3026127991],"iteration":335,"passed_time":2.099525552,"remaining_time":4.149062401},
{"learn":[0.3019693384],"iteration":336,"passed_time":2.107341395,"remaining_time":4.145897166},
{"learn":[0.3015399012],"iteration":337,"passed_time":2.11880133,"remaining_time":4.149841658},
{"learn":[0.3010761605],"iteration":338,"passed_time":2.124359266,"remaining_time":4.142187242},
{"learn":[0.3005965961],"iteration":339,"passed_time":2.135757782,"remaining_time":4.145882753},
{"learn":[0.3000285878],"iteration":340,"passed_time":2.151502076,"remaining_time":4.157888176},
{"learn":[0.2995065286],"iteration":341,"passed_time":2.157186551,"remaining_time":4.150376464},
{"learn":[0.2990922659],"iteration":342,"passed_time":2.169058006,"remaining_time":4.154726269},
{"learn":[0.2985480387],"iteration":343,"passed_time":2.174711877,"remaining_time":4.147124974},
{"learn":[0.2981587807],"iteration":344,"passed_time":2.187285033,"remaining_time":4.152671584},
{"learn":[0.2975713625],"iteration":345,"passed_time":2.20084949,"remaining_time":4.159987187},
{"learn":[0.29705703],"iteration":346,"passed_time":2.217491303,"remaining_time":4.172973546},
{"learn":[0.296651273],"iteration":347,"passed_time":2.223453021,"remaining_time":4.165779798},
{"learn":[0.2961309361],"iteration":348,"passed_time":2.235099456,"remaining_time":4.16919698},
{"learn":[0.2958909964],"iteration":349,"passed_time":2.246734741,"remaining_time":4.172507377},
{"learn":[0.295274005],"iteration":350,"passed_time":2.252291478,"remaining_time":4.16449336},
{"learn":[0.2947906051],"iteration":351,"passed_time":2.262667385,"remaining_time":4.165364958},
{"learn":[0.2943791845],"iteration":352,"passed_time":2.26717765,"remaining_time":4.155421925},
{"learn":[0.2939804163],"iteration":353,"passed_time":2.277438788,"remaining_time":4.156004116},
{"learn":[0.2936262884],"iteration":354,"passed_time":2.28344881,"remaining_time":4.148801359},
{"learn":[0.2930884385],"iteration":355,"passed_time":2.292757,"remaining_time":4.147571652},
{"learn":[0.2926671908],"iteration":356,"passed_time":2.298040312,"remaining_time":4.139047396},
{"learn":[0.292150228],"iteration":357,"passed_time":2.302335826,"remaining_time":4.128769834},
{"learn":[0.2915497948],"iteration":358,"passed_time":2.311689336,"remaining_time":4.127556726},
{"learn":[0.2910647894],"iteration":359,"passed_time":2.316238263,"remaining_time":4.117756912},
{"learn":[0.2907498295],"iteration":360,"passed_time":2.324295717,"remaining_time":4.114196574},
{"learn":[0.2904545235],"iteration":361,"passed_time":2.328953893,"remaining_time":4.104620396},
{"learn":[0.2898986789],"iteration":362,"passed_time":2.333266649,"remaining_time":4.094465167},
{"learn":[0.2893212211],"iteration":363,"passed_time":2.34170393,"remaining_time":4.091548625},
{"learn":[0.2888439382],"iteration":364,"passed_time":2.346310786,"remaining_time":4.081937943},
{"learn":[0.2884035629],"iteration":365,"passed_time":2.35080901,"remaining_time":4.072166427},
{"learn":[0.2881772952],"iteration":366,"passed_time":2.360181656,"remaining_time":4.07083103},
{"learn":[0.2876492092],"iteration":367,"passed_time":2.366624714,"remaining_time":4.064420704},
{"learn":[0.2873707709],"iteration":368,"passed_time":2.377413931,"remaining_time":4.06544225},
{"learn":[0.2870358818],"iteration":369,"passed_time":2.382551519,"remaining_time":4.056776911},
{"learn":[0.2867663964],"iteration":370,"passed_time":2.394915531,"remaining_time":4.060382396},
{"learn":[0.28646349],"iteration":371,"passed_time":2.403193346,"remaining_time":4.057003821},
{"learn":[0.2860188603],"iteration":372,"passed_time":2.41245167,"remaining_time":4.055247177},
{"learn":[0.2854973317],"iteration":373,"passed_time":2.42154905,"remaining_time":4.05318103},
{"learn":[0.2849470755],"iteration":374,"passed_time":2.429198268,"remaining_time":4.04866378},
{"learn":[0.284766936],"iteration":375,"passed_time":2.439129978,"remaining_time":4.047917836},
{"learn":[0.2843179399],"iteration":376,"passed_time":2.444152092,"remaining_time":4.039009956},
{"learn":[0.2840422],"iteration":377,"passed_time":2.452730236,"remaining_time":4.035974092},
{"learn":[0.2838626908],"iteration":378,"passed_time":2.460562421,"remaining_time":4.031686712},
{"learn":[0.2835619307],"iteration":379,"passed_time":2.468899007,"remaining_time":4.028203643},
{"learn":[0.2833235006],"iteration":380,"passed_time":2.474793638,"remaining_time":4.020727722},
{"learn":[0.2828069175],"iteration":381,"passed_time":2.486158443,"remaining_time":4.022109733},
{"learn":[0.282340493],"iteration":382,"passed_time":2.494364796,"remaining_time":4.018337022},
{"learn":[0.2819020502],"iteration":383,"passed_time":2.503638162,"remaining_time":4.016252884},
{"learn":[0.2814978033],"iteration":384,"passed_time":2.507926065,"remaining_time":4.00616761},
{"learn":[0.2810104909],"iteration":385,"passed_time":2.514220335,"remaining_time":3.99930385},
{"learn":[0.2807075311],"iteration":386,"passed_time":2.520734628,"remaining_time":3.992791542},
{"learn":[0.2801375111],"iteration":387,"passed_time":2.524953144,"remaining_time":3.982658052},
{"learn":[0.2799774841],"iteration":388,"passed_time":2.532064743,"remaining_time":3.977099121},
{"learn":[0.279363247],"iteration":389,"passed_time":2.536284425,"remaining_time":3.967008973},
{"learn":[0.2789944526],"iteration":390,"passed_time":2.540515722,"remaining_time":3.956966944},
{"learn":[0.2786166568],"iteration":391,"passed_time":2.54737939,"remaining_time":3.951037421},
{"learn":[0.2782755604],"iteration":392,"passed_time":2.551650822,"remaining_time":3.941099362},
{"learn":[0.2779171942],"iteration":393,"passed_time":2.556067022,"remaining_time":3.931412729},
{"learn":[0.2775817952],"iteration":394,"passed_time":2.562474302,"remaining_time":3.924802412},
{"learn":[0.2771295254],"iteration":395,"passed_time":2.566705305,"remaining_time":3.914873747},
{"learn":[0.2765613428],"iteration":396,"passed_time":2.570893524,"remaining_time":3.904908804},
{"learn":[0.276046424],"iteration":397,"passed_time":2.575240388,"remaining_time":3.895212848},
{"learn":[0.2755096071],"iteration":398,"passed_time":2.581596964,"remaining_time":3.888570865},
{"learn":[0.2752102335],"iteration":399,"passed_time":2.585886955,"remaining_time":3.878830432},
{"learn":[0.2748724133],"iteration":400,"passed_time":2.590303748,"remaining_time":3.869306597},
{"learn":[0.2742573344],"iteration":401,"passed_time":2.597108647,"remaining_time":3.863360625},
{"learn":[0.2737901925],"iteration":402,"passed_time":2.601666646,"remaining_time":3.854081856},
{"learn":[0.2733676731],"iteration":403,"passed_time":2.605959193,"remaining_time":3.844434849},
{"learn":[0.2728406952],"iteration":404,"passed_time":2.612393886,"remaining_time":3.837961388},
{"learn":[0.2724082376],"iteration":405,"passed_time":2.616736763,"remaining_time":3.828427678},
{"learn":[0.2719203403],"iteration":406,"passed_time":2.6207879,"remaining_time":3.818494409},
{"learn":[0.2715803342],"iteration":407,"passed_time":2.627015338,"remaining_time":3.811747746},
{"learn":[0.271244392],"iteration":408,"passed_time":2.632112322,"remaining_time":3.803370128},
{"learn":[0.2705908457],"iteration":409,"passed_time":2.636234396,"remaining_time":3.793605595},
{"learn":[0.2700268743],"iteration":410,"passed_time":2.64180713,"remaining_time":3.785947445},
{"learn":[0.2698027622],"iteration":411,"passed_time":2.64644124,"remaining_time":3.776959828},
{"learn":[0.2695105271],"iteration":412,"passed_time":2.650429157,"remaining_time":3.767074855},
{"learn":[0.2690022188],"iteration":413,"passed_time":2.654675758,"remaining_time":3.757584527},
{"learn":[0.2686113048],"iteration":414,"passed_time":2.660635295,"remaining_time":3.750534091},
{"learn":[0.26815672],"iteration":415,"passed_time":2.664804063,"remaining_time":3.740974934},
{"learn":[0.267980446],"iteration":416,"passed_time":2.668822049,"remaining_time":3.731230827},
{"learn":[0.2674600146],"iteration":417,"passed_time":2.675214448,"remaining_time":3.724820116},
{"learn":[0.267059525],"iteration":418,"passed_time":2.679417949,"remaining_time":3.715374292},
{"learn":[0.2668443997],"iteration":419,"passed_time":2.683663987,"remaining_time":3.706012173},
{"learn":[0.2664570307],"iteration":420,"passed_time":2.690020028,"remaining_time":3.699576238},
{"learn":[0.2660924202],"iteration":421,"passed_time":2.6942815,"remaining_time":3.690271818},
{"learn":[0.2657819765],"iteration":422,"passed_time":2.698660316,"remaining_time":3.681151306},
{"learn":[0.265578964],"iteration":423,"passed_time":2.70317962,"remaining_time":3.672244012},
{"learn":[0.2651413527],"iteration":424,"passed_time":2.709344369,"remaining_time":3.665583559},
{"learn":[0.2646771866],"iteration":425,"passed_time":2.714144409,"remaining_time":3.657086597},
{"learn":[0.264217196],"iteration":426,"passed_time":2.71829939,"remaining_time":3.647741336},
{"learn":[0.2638044411],"iteration":427,"passed_time":2.725015132,"remaining_time":3.641842652},
{"learn":[0.2634554595],"iteration":428,"passed_time":2.72943404,"remaining_time":3.632883069},
{"learn":[0.2630670038],"iteration":429,"passed_time":2.733827721,"remaining_time":3.623911165},
{"learn":[0.2624776972],"iteration":430,"passed_time":2.739808622,"remaining_time":3.617055931},
{"learn":[0.2621414651],"iteration":431,"passed_time":2.744238869,"remaining_time":3.608165921},
{"learn":[0.2617391807],"iteration":432,"passed_time":2.748368192,"remaining_time":3.598902459},
{"learn":[0.2612898381],"iteration":433,"passed_time":2.753988424,"remaining_time":3.591607024},
{"learn":[0.2610869667],"iteration":434,"passed_time":2.758326995,"remaining_time":3.582654603},
{"learn":[0.2607425364],"iteration":435,"passed_time":2.762617985,"remaining_time":3.573661797},
{"learn":[0.2605736048],"iteration":436,"passed_time":2.766671736,"remaining_time":3.564384868},
{"learn":[0.2601902881],"iteration":437,"passed_time":2.772356884,"remaining_time":3.557225043},
{"learn":[0.259793421],"iteration":438,"passed_time":2.776758968,"remaining_time":3.548432304},
{"learn":[0.2595546621],"iteration":439,"passed_time":2.781019583,"remaining_time":3.539479469},
{"learn":[0.2589167],"iteration":440,"passed_time":2.787179818,"remaining_time":3.532955824},
{"learn":[0.2586839348],"iteration":441,"passed_time":2.791427084,"remaining_time":3.524018808},
{"learn":[0.2584944397],"iteration":442,"passed_time":2.795598575,"remaining_time":3.515007689},
{"learn":[0.2580983292],"iteration":443,"passed_time":2.801242124,"remaining_time":3.507861759},
{"learn":[0.2577726039],"iteration":444,"passed_time":2.806727653,"remaining_time":3.500525499},
{"learn":[0.2575695261],"iteration":445,"passed_time":2.810896165,"remaining_time":3.491561604},
{"learn":[0.2573589063],"iteration":446,"passed_time":2.816502903,"remaining_time":3.484398446},
{"learn":[0.2569722134],"iteration":447,"passed_time":2.821208596,"remaining_time":3.47613202},
{"learn":[0.2566179461],"iteration":448,"passed_time":2.825606151,"remaining_time":3.467503316},
{"learn":[0.2561699988],"iteration":449,"passed_time":2.829866106,"remaining_time":3.458725241},
{"learn":[0.2559258871],"iteration":450,"passed_time":2.836077271,"remaining_time":3.452342399},
{"learn":[0.2558233243],"iteration":451,"passed_time":2.839533998,"remaining_time":3.442620865},
{"learn":[0.2554983279],"iteration":452,"passed_time":2.843789451,"remaining_time":3.433891456},
{"learn":[0.2550332699],"iteration":453,"passed_time":2.849160886,"remaining_time":3.426523885},
{"learn":[0.2545507157],"iteration":454,"passed_time":2.853408954,"remaining_time":3.417819517},
{"learn":[0.2543430669],"iteration":455,"passed_time":2.856399084,"remaining_time":3.407633996},
{"learn":[0.2540920477],"iteration":456,"passed_time":2.860611852,"remaining_time":3.398932682},
{"learn":[0.2536255022],"iteration":457,"passed_time":2.866512959,"remaining_time":3.39224896},
{"learn":[0.2533356839],"iteration":458,"passed_time":2.870833229,"remaining_time":3.383705396},
{"learn":[0.2529994965],"iteration":459,"passed_time":2.875203109,"remaining_time":3.375238433},
{"learn":[0.2525042428],"iteration":460,"passed_time":2.880569777,"remaining_time":3.367954686},
{"learn":[0.2521234234],"iteration":461,"passed_time":2.886207366,"remaining_time":3.360994725},
{"learn":[0.2519445449],"iteration":462,"passed_time":2.890933566,"remaining_time":3.352983423},
{"learn":[0.251499493],"iteration":463,"passed_time":2.897193963,"remaining_time":3.346758543},
{"learn":[0.2510494346],"iteration":464,"passed_time":2.901401155,"remaining_time":3.338171221},
{"learn":[0.2507798393],"iteration":465,"passed_time":2.905665898,"remaining_time":3.329668648},
{"learn":[0.250379635],"iteration":466,"passed_time":2.910321134,"remaining_time":3.321629903},
{"learn":[0.2500326377],"iteration":467,"passed_time":2.91730349,"remaining_time":3.316250976},
{"learn":[0.2498036407],"iteration":468,"passed_time":2.922103115,"remaining_time":3.308393932},
{"learn":[0.2495243798],"iteration":469,"passed_time":2.926394105,"remaining_time":3.299976331},
{"learn":[0.249143206],"iteration":470,"passed_time":2.932204488,"remaining_time":3.293282748},
{"learn":[0.2487991938],"iteration":471,"passed_time":2.936616448,"remaining_time":3.285028569},
{"learn":[0.248501877],"iteration":472,"passed_time":2.94087993,"remaining_time":3.276625207},
{"learn":[0.2481831056],"iteration":473,"passed_time":2.946826823,"remaining_time":3.270107403},
{"learn":[0.2476616771],"iteration":474,"passed_time":2.951359184,"remaining_time":3.262028572},
{"learn":[0.2474722004],"iteration":475,"passed_time":2.955794688,"remaining_time":3.253858018},
{"learn":[0.2469219752],"iteration":476,"passed_time":2.961993112,"remaining_time":3.247636054},
{"learn":[0.24658459],"iteration":477,"passed_time":2.966960953,"remaining_time":3.24007033},
{"learn":[0.2460305798],"iteration":478,"passed_time":2.971609139,"remaining_time":3.23216777},
{"learn":[0.2455421386],"iteration":479,"passed_time":2.977313611,"remaining_time":3.225423079},
{"learn":[0.2453138],"iteration":480,"passed_time":2.981780906,"remaining_time":3.217347797},
{"learn":[0.2450642674],"iteration":481,"passed_time":2.986205992,"remaining_time":3.209242124},
{"learn":[0.2448079597],"iteration":482,"passed_time":2.991278099,"remaining_time":3.201844259},
{"learn":[0.2444254006],"iteration":483,"passed_time":2.996760285,"remaining_time":3.194893197},
{"learn":[0.2443291496],"iteration":484,"passed_time":3.001152133,"remaining_time":3.186790409},
{"learn":[0.2439641535],"iteration":485,"passed_time":3.005469722,"remaining_time":3.178624356},
{"learn":[0.2437973484],"iteration":486,"passed_time":3.013630724,"remaining_time":3.174522714},
{"learn":[0.2433559706],"iteration":487,"passed_time":3.020427608,"remaining_time":3.168973228},
{"learn":[0.2428542902],"iteration":488,"passed_time":3.02729409,"remaining_time":3.163491371},
{"learn":[0.2424157033],"iteration":489,"passed_time":3.034171507,"remaining_time":3.158015242},
{"learn":[0.2420167851],"iteration":490,"passed_time":3.039406011,"remaining_time":3.150830264},
{"learn":[0.2418300463],"iteration":491,"passed_time":3.048181927,"remaining_time":3.147309795},
{"learn":[0.2414820866],"iteration":492,"passed_time":3.053547217,"remaining_time":3.140260525},
{"learn":[0.2410215149],"iteration":493,"passed_time":3.065416911,"remaining_time":3.13988048},
{"learn":[0.2408149245],"iteration":494,"passed_time":3.07887944,"remaining_time":3.141079024},
{"learn":[0.2404667568],"iteration":495,"passed_time":3.084502456,"remaining_time":3.134252496},
{"learn":[0.2402444145],"iteration":496,"passed_time":3.094789399,"remaining_time":3.132151041},
{"learn":[0.2398519308],"iteration":497,"passed_time":3.100496135,"remaining_time":3.125399718},
{"learn":[0.23937614],"iteration":498,"passed_time":3.112253287,"remaining_time":3.124727249},
{"learn":[0.2390316128],"iteration":499,"passed_time":3.117647877,"remaining_time":3.117647877},
{"learn":[0.2386034849],"iteration":500,"passed_time":3.12894104,"remaining_time":3.116450258},
{"learn":[0.2381749857],"iteration":501,"passed_time":3.134427134,"remaining_time":3.109451619},
{"learn":[0.2379124385],"iteration":502,"passed_time":3.149030538,"remaining_time":3.111467549},
{"learn":[0.2376555615],"iteration":503,"passed_time":3.165190753,"remaining_time":3.11494963},
{"learn":[0.237252661],"iteration":504,"passed_time":3.179104633,"remaining_time":3.116152066},
{"learn":[0.2367780128],"iteration":505,"passed_time":3.184412403,"remaining_time":3.108892742},
{"learn":[0.2363660058],"iteration":506,"passed_time":3.19397501,"remaining_time":3.105778462},
{"learn":[0.2358116176],"iteration":507,"passed_time":3.205581525,"remaining_time":3.104618327},
{"learn":[0.2357160021],"iteration":508,"passed_time":3.211536649,"remaining_time":3.097965608},
{"learn":[0.2353494934],"iteration":509,"passed_time":3.223360318,"remaining_time":3.096954031},
{"learn":[0.234987131],"iteration":510,"passed_time":3.229405384,"remaining_time":3.090370319},
{"learn":[0.2347777765],"iteration":511,"passed_time":3.240095223,"remaining_time":3.088215759},
{"learn":[0.234522186],"iteration":512,"passed_time":3.245559255,"remaining_time":3.081066973},
{"learn":[0.2339875812],"iteration":513,"passed_time":3.257682497,"remaining_time":3.080221194},
{"learn":[0.2335071485],"iteration":514,"passed_time":3.263445123,"remaining_time":3.073341523},
{"learn":[0.2332233446],"iteration":515,"passed_time":3.273687192,"remaining_time":3.070667832},
{"learn":[0.23297373],"iteration":516,"passed_time":3.283499697,"remaining_time":3.067563547},
{"learn":[0.2325931171],"iteration":517,"passed_time":3.290391072,"remaining_time":3.061715245},
{"learn":[0.2320855479],"iteration":518,"passed_time":3.30166514,"remaining_time":3.059924725},
{"learn":[0.2319140827],"iteration":519,"passed_time":3.307389364,"remaining_time":3.052974797},
{"learn":[0.2315989272],"iteration":520,"passed_time":3.322179301,"remaining_time":3.054364463},
{"learn":[0.2311450973],"iteration":521,"passed_time":3.334798624,"remaining_time":3.053704487},
{"learn":[0.2306770792],"iteration":522,"passed_time":3.340795307,"remaining_time":3.046958626},
{"learn":[0.2303508909],"iteration":523,"passed_time":3.352611874,"remaining_time":3.045502389},
{"learn":[0.2301388918],"iteration":524,"passed_time":3.357973208,"remaining_time":3.038166236},
{"learn":[0.2299327088],"iteration":525,"passed_time":3.370666952,"remaining_time":3.037445124},
{"learn":[0.2296025302],"iteration":526,"passed_time":3.381675508,"remaining_time":3.035166064},
{"learn":[0.229288669],"iteration":527,"passed_time":3.387996907,"remaining_time":3.028663902},
{"learn":[0.2290540307],"iteration":528,"passed_time":3.397914788,"remaining_time":3.025364585},
{"learn":[0.228798019],"iteration":529,"passed_time":3.404321867,"remaining_time":3.018926939},
{"learn":[0.228407862],"iteration":530,"passed_time":3.414545788,"remaining_time":3.015860593},
{"learn":[0.2279962109],"iteration":531,"passed_time":3.41908503,"remaining_time":3.00776653},
{"learn":[0.2276703061],"iteration":532,"passed_time":3.425420479,"remaining_time":3.001259594},
{"learn":[0.227492596],"iteration":533,"passed_time":3.431774566,"remaining_time":2.994769565},
{"learn":[0.2273046868],"iteration":534,"passed_time":3.436058451,"remaining_time":2.98648071},
{"learn":[0.2268518134],"iteration":535,"passed_time":3.443664059,"remaining_time":2.98108232},
{"learn":[0.2265556098],"iteration":536,"passed_time":3.450714925,"remaining_time":2.975197412},
{"learn":[0.2263435089],"iteration":537,"passed_time":3.459139569,"remaining_time":2.970487882},
{"learn":[0.2261900785],"iteration":538,"passed_time":3.465868239,"remaining_time":2.964314023},
{"learn":[0.2258488937],"iteration":539,"passed_time":3.470356484,"remaining_time":2.956229597},
{"learn":[0.2256403417],"iteration":540,"passed_time":3.477625552,"remaining_time":2.950517797},
{"learn":[0.2253070094],"iteration":541,"passed_time":3.48199623,"remaining_time":2.942351058},
{"learn":[0.2251547104],"iteration":542,"passed_time":3.486334369,"remaining_time":2.934170914},
{"learn":[0.2247855835],"iteration":543,"passed_time":3.493472271,"remaining_time":2.928351756},
{"learn":[0.2242717292],"iteration":544,"passed_time":3.497573581,"remaining_time":2.919992622},
{"learn":[0.2240668717],"iteration":545,"passed_time":3.501741802,"remaining_time":2.911704722},
{"learn":[0.2236842974],"iteration":546,"passed_time":3.508691065,"remaining_time":2.905735014},
{"learn":[0.2233260746],"iteration":547,"passed_time":3.513955777,"remaining_time":2.898372283},
{"learn":[0.223176673],"iteration":548,"passed_time":3.518153971,"remaining_time":2.890141058},
{"learn":[0.2228418304],"iteration":549,"passed_time":3.524726359,"remaining_time":2.883867021},
{"learn":[0.2224592347],"iteration":550,"passed_time":3.529410399,"remaining_time":2.87605312},
{"learn":[0.2220954732],"iteration":551,"passed_time":3.533508993,"remaining_time":2.867775414},
{"learn":[0.2219303714],"iteration":552,"passed_time":3.539493312,"remaining_time":2.86103709},
{"learn":[0.2217345604],"iteration":553,"passed_time":3.543877839,"remaining_time":2.853013567},
{"learn":[0.221535839],"iteration":554,"passed_time":3.54827867,"remaining_time":2.845016231},
{"learn":[0.2211207424],"iteration":555,"passed_time":3.553925436,"remaining_time":2.838026787},
{"learn":[0.2208030259],"iteration":556,"passed_time":3.558351308,"remaining_time":2.830071148},
{"learn":[0.220324348],"iteration":557,"passed_time":3.562452505,"remaining_time":2.821870981},
{"learn":[0.220068795],"iteration":558,"passed_time":3.566592899,"remaining_time":2.813716401},
{"learn":[0.2199203997],"iteration":559,"passed_time":3.572450995,"remaining_time":2.806925782},
{"learn":[0.2196133795],"iteration":560,"passed_time":3.576662164,"remaining_time":2.798849715},
{"learn":[0.2192186432],"iteration":561,"passed_time":3.580921131,"remaining_time":2.790824653},
{"learn":[0.2189883775],"iteration":562,"passed_time":3.5865487,"remaining_time":2.783875278},
{"learn":[0.2186355978],"iteration":563,"passed_time":3.590660307,"remaining_time":2.775758677},
{"learn":[0.2185215057],"iteration":564,"passed_time":3.594872585,"remaining_time":2.76773376},
{"learn":[0.2183246555],"iteration":565,"passed_time":3.599058727,"remaining_time":2.759702275},
{"learn":[0.218046969],"iteration":566,"passed_time":3.605059433,"remaining_time":2.753070078},
{"learn":[0.2178962222],"iteration":567,"passed_time":3.60924916,"remaining_time":2.745062741},
{"learn":[0.2176820866],"iteration":568,"passed_time":3.613442001,"remaining_time":2.737071182},
{"learn":[0.2172878905],"iteration":569,"passed_time":3.619342859,"remaining_time":2.730381455},
{"learn":[0.2170647154],"iteration":570,"passed_time":3.624527798,"remaining_time":2.723156612},
{"learn":[0.2168770359],"iteration":571,"passed_time":3.628823351,"remaining_time":2.715273416},
{"learn":[0.216498268],"iteration":572,"passed_time":3.634320761,"remaining_time":2.708298368},
{"learn":[0.2162591561],"iteration":573,"passed_time":3.638747549,"remaining_time":2.700533895},
{"learn":[0.2161611489],"iteration":574,"passed_time":3.642061103,"remaining_time":2.691958206},
{"learn":[0.2160122052],"iteration":575,"passed_time":3.646206696,"remaining_time":2.684013263},
{"learn":[0.2156992608],"iteration":576,"passed_time":3.651962114,"remaining_time":2.677261654},
{"learn":[0.2154238746],"iteration":577,"passed_time":3.656179593,"remaining_time":2.669390637},
{"learn":[0.2151154926],"iteration":578,"passed_time":3.660462002,"remaining_time":2.661579452},
{"learn":[0.2149326661],"iteration":579,"passed_time":3.66575133,"remaining_time":2.654509584},
{"learn":[0.2146052074],"iteration":580,"passed_time":3.670106722,"remaining_time":2.646772318},
{"learn":[0.2142184577],"iteration":581,"passed_time":3.674195092,"remaining_time":2.638854894},
{"learn":[0.2138750204],"iteration":582,"passed_time":3.67845274,"remaining_time":2.631071686},
{"learn":[0.2135515986],"iteration":583,"passed_time":3.684214941,"remaining_time":2.624372287},
{"learn":[0.2133559669],"iteration":584,"passed_time":3.688443043,"remaining_time":2.616587799},
{"learn":[0.2131528205],"iteration":585,"passed_time":3.692606903,"remaining_time":2.608770065},
{"learn":[0.2128615346],"iteration":586,"passed_time":3.698056487,"remaining_time":2.601869385},
{"learn":[0.2125718539],"iteration":587,"passed_time":3.702358646,"remaining_time":2.594169664},
{"learn":[0.2123217591],"iteration":588,"passed_time":3.70663965,"remaining_time":2.586466716},
{"learn":[0.2120010456],"iteration":589,"passed_time":3.710859545,"remaining_time":2.578732904},
{"learn":[0.2117449205],"iteration":590,"passed_time":3.718002709,"remaining_time":2.573034024},
{"learn":[0.2115115069],"iteration":591,"passed_time":3.723318439,"remaining_time":2.566070816},
{"learn":[0.2111955794],"iteration":592,"passed_time":3.729777428,"remaining_time":2.55989783},
{"learn":[0.2109549887],"iteration":593,"passed_time":3.735987135,"remaining_time":2.553553496},
{"learn":[0.2105769621],"iteration":594,"passed_time":3.740248539,"remaining_time":2.545883459},
{"learn":[0.2102429512],"iteration":595,"passed_time":3.745778247,"remaining_time":2.539084584},
{"learn":[0.2099362062],"iteration":596,"passed_time":3.749995137,"remaining_time":2.531403753},
{"learn":[0.209663181],"iteration":597,"passed_time":3.754353088,"remaining_time":2.523829334},
{"learn":[0.2091742289],"iteration":598,"passed_time":3.758475157,"remaining_time":2.516107743},
{"learn":[0.208927786],"iteration":599,"passed_time":3.764221544,"remaining_time":2.509481029},
{"learn":[0.2085381206],"iteration":600,"passed_time":3.768556095,"remaining_time":2.501919937},
{"learn":[0.2081966672],"iteration":601,"passed_time":3.773001185,"remaining_time":2.494442644},
{"learn":[0.2080699032],"iteration":602,"passed_time":3.778709197,"remaining_time":2.487806884},
{"learn":[0.2080199647],"iteration":603,"passed_time":3.782184969,"remaining_time":2.479710675},
{"learn":[0.207833219],"iteration":604,"passed_time":3.786396969,"remaining_time":2.472110418},
{"learn":[0.2076819541],"iteration":605,"passed_time":3.790603326,"remaining_time":2.464517674},
{"learn":[0.2073976954],"iteration":606,"passed_time":3.796386608,"remaining_time":2.457957062},
{"learn":[0.2070224924],"iteration":607,"passed_time":3.800746236,"remaining_time":2.450481126},
{"learn":[0.2065605566],"iteration":608,"passed_time":3.805086113,"remaining_time":2.443002743},
{"learn":[0.2062604915],"iteration":609,"passed_time":3.810630762,"remaining_time":2.436304913},
{"learn":[0.2059231592],"iteration":610,"passed_time":3.814911548,"remaining_time":2.428806206},
{"learn":[0.205724787],"iteration":611,"passed_time":3.819117968,"remaining_time":2.421270869},
{"learn":[0.2055388386],"iteration":612,"passed_time":3.82396069,"remaining_time":2.414148103},
{"learn":[0.2053706249],"iteration":613,"passed_time":3.829769378,"remaining_time":2.407640032},
{"learn":[0.2052517167],"iteration":614,"passed_time":3.833908427,"remaining_time":2.400089015},
{"learn":[0.2050381422],"iteration":615,"passed_time":3.838139689,"remaining_time":2.392606559},
{"learn":[0.2047235987],"iteration":616,"passed_time":3.844161433,"remaining_time":2.386246076},
{"learn":[0.2046939169],"iteration":617,"passed_time":3.847520552,"remaining_time":2.378240859},
{"learn":[0.2043287317],"iteration":618,"passed_time":3.851795644,"remaining_time":2.370814443},
{"learn":[0.2040289071],"iteration":619,"passed_time":3.857504882,"remaining_time":2.364277186},
{"learn":[0.2037603145],"iteration":620,"passed_time":3.861814962,"remaining_time":2.356888681},
{"learn":[0.2035387475],"iteration":621,"passed_time":3.86610734,"remaining_time":2.349499316},
{"learn":[0.2035321825],"iteration":622,"passed_time":3.868448763,"remaining_time":2.340939299},
{"learn":[0.2032967119],"iteration":623,"passed_time":3.873785731,"remaining_time":2.334204222},
{"learn":[0.2029851706],"iteration":624,"passed_time":3.878382739,"remaining_time":2.327029643},
{"learn":[0.2026533529],"iteration":625,"passed_time":3.882725445,"remaining_time":2.319711368},
{"learn":[0.2022577338],"iteration":626,"passed_time":3.887989884,"remaining_time":2.31295092},
{"learn":[0.2020224638],"iteration":627,"passed_time":3.892487252,"remaining_time":2.305740856},
{"learn":[0.2017066446],"iteration":628,"passed_time":3.896588982,"remaining_time":2.298306061},
{"learn":[0.2014091695],"iteration":629,"passed_time":3.900653637,"remaining_time":2.290860073},
{"learn":[0.2011719087],"iteration":630,"passed_time":3.906881189,"remaining_time":2.284689633},
{"learn":[0.2009846115],"iteration":631,"passed_time":3.911274884,"remaining_time":2.277451198},
{"learn":[0.2008284083],"iteration":632,"passed_time":3.915555758,"remaining_time":2.27015634},
{"learn":[0.2005907025],"iteration":633,"passed_time":3.92140213,"remaining_time":2.263774731},
{"learn":[0.200264662],"iteration":634,"passed_time":3.926960822,"remaining_time":2.257229449},
{"learn":[0.2000025347],"iteration":635,"passed_time":3.931458066,"remaining_time":2.250079773},
{"learn":[0.1996447139],"iteration":636,"passed_time":3.937208191,"remaining_time":2.243652392},
{"learn":[0.1992855599],"iteration":637,"passed_time":3.941785997,"remaining_time":2.236561961},
{"learn":[0.1990443121],"iteration":638,"passed_time":3.94617609,"remaining_time":2.229373346},
{"learn":[0.1989232193],"iteration":639,"passed_time":3.950193827,"remaining_time":2.221984028},
{"learn":[0.1985009417],"iteration":640,"passed_time":3.956169104,"remaining_time":2.215701573},
{"learn":[0.1983210692],"iteration":641,"passed_time":3.960785263,"remaining_time":2.208662187},
{"learn":[0.1979680283],"iteration":642,"passed_time":3.965093406,"remaining_time":2.201459325},
{"learn":[0.1977167505],"iteration":643,"passed_time":3.971446093,"remaining_time":2.195395666},
{"learn":[0.1975819066],"iteration":644,"passed_time":3.97597543,"remaining_time":2.188327562},
{"learn":[0.1974254823],"iteration":645,"passed_time":3.980651257,"remaining_time":2.181347593},
{"learn":[0.1970117665],"iteration":646,"passed_time":3.986961926,"remaining_time":2.175266708},
{"learn":[0.1967999213],"iteration":647,"passed_time":3.993626947,"remaining_time":2.169377601},
{"learn":[0.1966196303],"iteration":648,"passed_time":3.998396633,"remaining_time":2.162461045},
{"learn":[0.1961977053],"iteration":649,"passed_time":4.006565078,"remaining_time":2.157381196},
{"learn":[0.1959047096],"iteration":650,"passed_time":4.012871093,"remaining_time":2.151293413},
{"learn":[0.1956811083],"iteration":651,"passed_time":4.026254177,"remaining_time":2.148982291},
{"learn":[0.1953248373],"iteration":652,"passed_time":4.033547431,"remaining_time":2.143401162},
{"learn":[0.195085932],"iteration":653,"passed_time":4.041317311,"remaining_time":2.138066957},
{"learn":[0.1948295163],"iteration":654,"passed_time":4.050986313,"remaining_time":2.133725615},
{"learn":[0.1946001976],"iteration":655,"passed_time":4.058502696,"remaining_time":2.128239219},
{"learn":[0.1944230992],"iteration":656,"passed_time":4.071521256,"remaining_time":2.125619164},
{"learn":[0.1940345194],"iteration":657,"passed_time":4.07801458,"remaining_time":2.119575967},
{"learn":[0.1937221378],"iteration":658,"passed_time":4.090082319,"remaining_time":2.116415889},
{"learn":[0.193483222],"iteration":659,"passed_time":4.095202522,"remaining_time":2.109649784},
{"learn":[0.1931381921],"iteration":660,"passed_time":4.109656117,"remaining_time":2.107675376},
{"learn":[0.1927086914],"iteration":661,"passed_time":4.122249598,"remaining_time":2.104713541},
{"learn":[0.1924849282],"iteration":662,"passed_time":4.133172894,"remaining_time":2.100873703},
{"learn":[0.1922913324],"iteration":663,"passed_time":4.141003726,"remaining_time":2.095447669},
{"learn":[0.1919804094],"iteration":664,"passed_time":4.156114179,"remaining_time":2.093681579},
{"learn":[0.1917606473],"iteration":665,"passed_time":4.172494059,"remaining_time":2.092512036},
{"learn":[0.1916177449],"iteration":666,"passed_time":4.181701017,"remaining_time":2.0877158},
{"learn":[0.1912986073],"iteration":667,"passed_time":4.189602372,"remaining_time":2.082257466},
{"learn":[0.1911164401],"iteration":668,"passed_time":4.200559672,"remaining_time":2.078303814},
{"learn":[0.1907956846],"iteration":669,"passed_time":4.20625579,"remaining_time":2.071737926},
{"learn":[0.1907031872],"iteration":670,"passed_time":4.216553415,"remaining_time":2.06743081},
{"learn":[0.1903229001],"iteration":671,"passed_time":4.221880924,"remaining_time":2.060679975},
{"learn":[0.1901819501],"iteration":672,"passed_time":4.228274695,"remaining_time":2.054451449},
{"learn":[0.1899647171],"iteration":673,"passed_time":4.234301862,"remaining_time":2.048045114},
{"learn":[0.189815876],"iteration":674,"passed_time":4.239055674,"remaining_time":2.041026806},
{"learn":[0.1896734994],"iteration":675,"passed_time":4.247118051,"remaining_time":2.03560096},
{"learn":[0.1895746755],"iteration":676,"passed_time":4.25163371,"remaining_time":2.028475168},
{"learn":[0.1893492984],"iteration":677,"passed_time":4.255716462,"remaining_time":2.021151476},
{"learn":[0.1892028714],"iteration":678,"passed_time":4.263469515,"remaining_time":2.01557248},
{"learn":[0.1888773218],"iteration":679,"passed_time":4.268029814,"remaining_time":2.008484619},
{"learn":[0.1886386982],"iteration":680,"passed_time":4.2724315,"remaining_time":2.00132988},
{"learn":[0.1883748355],"iteration":681,"passed_time":4.279297986,"remaining_time":1.995332492},
{"learn":[0.1880641186],"iteration":682,"passed_time":4.283621149,"remaining_time":1.988152129},
{"learn":[0.1879569135],"iteration":683,"passed_time":4.288144376,"remaining_time":1.981072548},
{"learn":[0.1876327281],"iteration":684,"passed_time":4.297025412,"remaining_time":1.976004387},
{"learn":[0.1873777107],"iteration":685,"passed_time":4.30128083,"remaining_time":1.968807844},
{"learn":[0.1871992896],"iteration":686,"passed_time":4.306482446,"remaining_time":1.962050954},
{"learn":[0.1870223257],"iteration":687,"passed_time":4.310995159,"remaining_time":1.954986177},
{"learn":[0.1867630558],"iteration":688,"passed_time":4.315502784,"remaining_time":1.947926511},
{"learn":[0.1866423637],"iteration":689,"passed_time":4.319833229,"remaining_time":1.940794639},
{"learn":[0.1863003218],"iteration":690,"passed_time":4.326871311,"remaining_time":1.934881672},
{"learn":[0.1861171712],"iteration":691,"passed_time":4.332089355,"remaining_time":1.928155377},
{"learn":[0.1858918136],"iteration":692,"passed_time":4.33734518,"remaining_time":1.921450174},
{"learn":[0.185713127],"iteration":693,"passed_time":4.342915656,"remaining_time":1.914887883},
{"learn":[0.1855163988],"iteration":694,"passed_time":4.347313219,"remaining_time":1.907813715},
{"learn":[0.1852154456],"iteration":695,"passed_time":4.351698571,"remaining_time":1.900741905},
{"learn":[0.1848926529],"iteration":696,"passed_time":4.358228845,"remaining_time":1.894610244},
{"learn":[0.1845668471],"iteration":697,"passed_time":4.36263369,"remaining_time":1.887557843},
{"learn":[0.1844382766],"iteration":698,"passed_time":4.367053195,"remaining_time":1.88051933},
{"learn":[0.1843771413],"iteration":699,"passed_time":4.373690233,"remaining_time":1.874438671},
{"learn":[0.1839612098],"iteration":700,"passed_time":4.378322526,"remaining_time":1.867501334},
{"learn":[0.1837898712],"iteration":701,"passed_time":4.382403118,"remaining_time":1.860336367},
{"learn":[0.1836477179],"iteration":702,"passed_time":4.389476261,"remaining_time":1.854444451},
{"learn":[0.1833987882],"iteration":703,"passed_time":4.39496792,"remaining_time":1.847884239},
{"learn":[0.1831851712],"iteration":704,"passed_time":4.400239836,"remaining_time":1.841235109},
{"learn":[0.1829442264],"iteration":705,"passed_time":4.409399096,"remaining_time":1.836208689},
{"learn":[0.1826386857],"iteration":706,"passed_time":4.414591504,"remaining_time":1.829526607},
{"learn":[0.1823544118],"iteration":707,"passed_time":4.424694542,"remaining_time":1.82487402},
{"learn":[0.1820104777],"iteration":708,"passed_time":4.430705623,"remaining_time":1.818526567},
{"learn":[0.1817591864],"iteration":709,"passed_time":4.441349847,"remaining_time":1.814072473},
{"learn":[0.1813620784],"iteration":710,"passed_time":4.447051958,"remaining_time":1.807592146},
{"learn":[0.1810937463],"iteration":711,"passed_time":4.457833288,"remaining_time":1.803168521},
{"learn":[0.1808985408],"iteration":712,"passed_time":4.463598863,"remaining_time":1.796708098},
{"learn":[0.1808053922],"iteration":713,"passed_time":4.474399647,"remaining_time":1.792266525},
{"learn":[0.180575199],"iteration":714,"passed_time":4.480871801,"remaining_time":1.786081767},
{"learn":[0.180396571],"iteration":715,"passed_time":4.49216234,"remaining_time":1.781807409},
{"learn":[0.1801659458],"iteration":716,"passed_time":4.500759675,"remaining_time":1.776450471},
{"learn":[0.1798665597],"iteration":717,"passed_time":4.508790947,"remaining_time":1.770862182},
{"learn":[0.1796300821],"iteration":718,"passed_time":4.520764575,"remaining_time":1.766807852},
{"learn":[0.1793149135],"iteration":719,"passed_time":4.526471,"remaining_time":1.760294278},
{"learn":[0.1789486667],"iteration":720,"passed_time":4.538037595,"remaining_time":1.756050609},
{"learn":[0.1786634672],"iteration":721,"passed_time":4.551445668,"remaining_time":1.7524957},
{"learn":[0.1784618419],"iteration":722,"passed_time":4.559436171,"remaining_time":1.746837924},
{"learn":[0.1780651426],"iteration":723,"passed_time":4.574319144,"remaining_time":1.743801221},
{"learn":[0.1778999687],"iteration":724,"passed_time":4.585580109,"remaining_time":1.739357972},
{"learn":[0.1776074963],"iteration":725,"passed_time":4.591331708,"remaining_time":1.73281665},
{"learn":[0.1772663942],"iteration":726,"passed_time":4.600523654,"remaining_time":1.727569405},
{"learn":[0.1770864888],"iteration":727,"passed_time":4.607639873,"remaining_time":1.721535777},
{"learn":[0.1768645392],"iteration":728,"passed_time":4.61823355,"remaining_time":1.716791896},
{"learn":[0.1766610808],"iteration":729,"passed_time":4.62417681,"remaining_time":1.710311971},
{"learn":[0.1764442016],"iteration":730,"passed_time":4.635145898,"remaining_time":1.705682964},
{"learn":[0.1761099967],"iteration":731,"passed_time":4.640738252,"remaining_time":1.699068103},
{"learn":[0.1758306653],"iteration":732,"passed_time":4.651751422,"remaining_time":1.6944306},
{"learn":[0.1755822744],"iteration":733,"passed_time":4.657398191,"remaining_time":1.687830952},
{"learn":[0.1754354959],"iteration":734,"passed_time":4.669300775,"remaining_time":1.683489395},
{"learn":[0.1751169793],"iteration":735,"passed_time":4.67483625,"remaining_time":1.676843437},
{"learn":[0.1749085167],"iteration":736,"passed_time":4.686279007,"remaining_time":1.672308519},
{"learn":[0.1747045762],"iteration":737,"passed_time":4.690952072,"remaining_time":1.665351549},
{"learn":[0.1744476298],"iteration":738,"passed_time":4.699628119,"remaining_time":1.659814532},
{"learn":[0.1742123471],"iteration":739,"passed_time":4.70407377,"remaining_time":1.652782676},
{"learn":[0.1739781141],"iteration":740,"passed_time":4.710399321,"remaining_time":1.646414877},
{"learn":[0.1737349384],"iteration":741,"passed_time":4.717396205,"remaining_time":1.640280621},
{"learn":[0.1734217909],"iteration":742,"passed_time":4.721888616,"remaining_time":1.633277758},
{"learn":[0.1731866],"iteration":743,"passed_time":4.730139366,"remaining_time":1.627574836},
{"learn":[0.172976418],"iteration":744,"passed_time":4.734503869,"remaining_time":1.620534881},
{"learn":[0.1727327914],"iteration":745,"passed_time":4.738787863,"remaining_time":1.613474688},
{"learn":[0.1724730829],"iteration":746,"passed_time":4.747770018,"remaining_time":1.608013139},
{"learn":[0.1722758125],"iteration":747,"passed_time":4.753941785,"remaining_time":1.601595361},
{"learn":[0.1720931224],"iteration":748,"passed_time":4.763489209,"remaining_time":1.596309468},
{"learn":[0.1717004333],"iteration":749,"passed_time":4.769547814,"remaining_time":1.589849271},
{"learn":[0.1713866215],"iteration":750,"passed_time":4.778910903,"remaining_time":1.584485772},
{"learn":[0.1711629431],"iteration":751,"passed_time":4.784270677,"remaining_time":1.577791394},
{"learn":[0.171030622],"iteration":752,"passed_time":4.789540334,"remaining_time":1.571070999},
{"learn":[0.1707160963],"iteration":753,"passed_time":4.795934239,"remaining_time":1.56472125},
{"learn":[0.1703734056],"iteration":754,"passed_time":4.800236599,"remaining_time":1.557692671},
{"learn":[0.1701886366],"iteration":755,"passed_time":4.806632208,"remaining_time":1.551346903},
{"learn":[0.1700213297],"iteration":756,"passed_time":4.811598552,"remaining_time":1.544542204},
{"learn":[0.1696957696],"iteration":757,"passed_time":4.816007841,"remaining_time":1.537564509},
{"learn":[0.1693679346],"iteration":758,"passed_time":4.82180148,"remaining_time":1.531033144},
{"learn":[0.1692786283],"iteration":759,"passed_time":4.827846178,"remaining_time":1.524583004},
{"learn":[0.1690105089],"iteration":760,"passed_time":4.832740451,"remaining_time":1.517772625},
{"learn":[0.1687711946],"iteration":761,"passed_time":4.83900682,"remaining_time":1.511395831},
{"learn":[0.168460809],"iteration":762,"passed_time":4.843506516,"remaining_time":1.504470569},
{"learn":[0.1682551197],"iteration":763,"passed_time":4.847700498,"remaining_time":1.497457222},
{"learn":[0.1680220297],"iteration":764,"passed_time":4.852799565,"remaining_time":1.490729278},
{"learn":[0.1678665902],"iteration":765,"passed_time":4.858270904,"remaining_time":1.48411931},
{"learn":[0.1677064839],"iteration":766,"passed_time":4.862501822,"remaining_time":1.477135495},
{"learn":[0.1674378512],"iteration":767,"passed_time":4.867041671,"remaining_time":1.470252171},
{"learn":[0.1673543406],"iteration":768,"passed_time":4.873329663,"remaining_time":1.463900068},
{"learn":[0.1671605904],"iteration":769,"passed_time":4.877866418,"remaining_time":1.457025034},
{"learn":[0.1669671286],"iteration":770,"passed_time":4.882205596,"remaining_time":1.450097382},
{"learn":[0.166880001],"iteration":771,"passed_time":4.888627324,"remaining_time":1.443791489},
{"learn":[0.1665305597],"iteration":772,"passed_time":4.893109167,"remaining_time":1.436915629},
{"learn":[0.1662947225],"iteration":773,"passed_time":4.897454022,"remaining_time":1.430005955},
{"learn":[0.166023376],"iteration":774,"passed_time":4.903220767,"remaining_time":1.423515706},
{"learn":[0.1657962919],"iteration":775,"passed_time":4.907766455,"remaining_time":1.416674853},
{"learn":[0.1654895695],"iteration":776,"passed_time":4.91200729,"remaining_time":1.409752414},
{"learn":[0.1652566675],"iteration":777,"passed_time":4.917195819,"remaining_time":1.40310729},
{"learn":[0.1650663511],"iteration":778,"passed_time":4.92345514,"remaining_time":1.396769687},
{"learn":[0.164792893],"iteration":779,"passed_time":4.928174821,"remaining_time":1.389998027},
{"learn":[0.164702791],"iteration":780,"passed_time":4.93329451,"remaining_time":1.383343787},
{"learn":[0.1644987235],"iteration":781,"passed_time":4.939574504,"remaining_time":1.377016933},
{"learn":[0.1642794161],"iteration":782,"passed_time":4.944248026,"remaining_time":1.370244983},
{"learn":[0.1642269179],"iteration":783,"passed_time":4.948368187,"remaining_time":1.363325929},
{"learn":[0.1640791226],"iteration":784,"passed_time":4.95323804,"remaining_time":1.356619336},
{"learn":[0.1639299013],"iteration":785,"passed_time":4.957664672,"remaining_time":1.349796743},
{"learn":[0.1638417831],"iteration":786,"passed_time":4.962113314,"remaining_time":1.342986196},
{"learn":[0.1635573768],"iteration":787,"passed_time":4.968696532,"remaining_time":1.33675592},
{"learn":[0.1634018153],"iteration":788,"passed_time":4.972872559,"remaining_time":1.329881001},
{"learn":[0.1633167375],"iteration":789,"passed_time":4.977349933,"remaining_time":1.32309302},
{"learn":[0.1631406725],"iteration":790,"passed_time":4.984164213,"remaining_time":1.316928344},
{"learn":[0.1629925962],"iteration":791,"passed_time":4.98862272,"remaining_time":1.310143341},
{"learn":[0.1627695202],"iteration":792,"passed_time":4.993595933,"remaining_time":1.30349856},
{"learn":[0.1624531336],"iteration":793,"passed_time":5.000057762,"remaining_time":1.297244205},
{"learn":[0.1622137152],"iteration":794,"passed_time":5.00447174,"remaining_time":1.290461266},
{"learn":[0.161964588],"iteration":795,"passed_time":5.008774527,"remaining_time":1.283655783},
{"learn":[0.1618180923],"iteration":796,"passed_time":5.016236861,"remaining_time":1.277661333},
{"learn":[0.1617045589],"iteration":797,"passed_time":5.021812396,"remaining_time":1.271185594},
{"learn":[0.1615893308],"iteration":798,"passed_time":5.02651953,"remaining_time":1.264493649},
{"learn":[0.1613898388],"iteration":799,"passed_time":5.033240852,"remaining_time":1.258310213},
{"learn":[0.1611687103],"iteration":800,"passed_time":5.037370879,"remaining_time":1.251481654},
{"learn":[0.1609910147],"iteration":801,"passed_time":5.041731494,"remaining_time":1.244716753},
{"learn":[0.1607460262],"iteration":802,"passed_time":5.048699293,"remaining_time":1.23859746},
{"learn":[0.160532794],"iteration":803,"passed_time":5.053242627,"remaining_time":1.231885019},
{"learn":[0.1604471155],"iteration":804,"passed_time":5.057529879,"remaining_time":1.225115933},
{"learn":[0.1603150125],"iteration":805,"passed_time":5.064357907,"remaining_time":1.218964558},
{"learn":[0.160057642],"iteration":806,"passed_time":5.068976481,"remaining_time":1.212283099},
{"learn":[0.1599800544],"iteration":807,"passed_time":5.073181258,"remaining_time":1.205508418},
{"learn":[0.1598236912],"iteration":808,"passed_time":5.08092487,"remaining_time":1.199575587},
{"learn":[0.1594921777],"iteration":809,"passed_time":5.085942385,"remaining_time":1.192998831},
{"learn":[0.1592022539],"iteration":810,"passed_time":5.090657159,"remaining_time":1.186355368},
{"learn":[0.1590085934],"iteration":811,"passed_time":5.096986697,"remaining_time":1.180090516},
{"learn":[0.1586869211],"iteration":812,"passed_time":5.101138575,"remaining_time":1.173324617},
{"learn":[0.1584659742],"iteration":813,"passed_time":5.105471763,"remaining_time":1.16660657},
{"learn":[0.1581506715],"iteration":814,"passed_time":5.111984922,"remaining_time":1.160389215},
{"learn":[0.1579383638],"iteration":815,"passed_time":5.116543511,"remaining_time":1.153730399},
{"learn":[0.1577380735],"iteration":816,"passed_time":5.120560187,"remaining_time":1.146955342},
{"learn":[0.1575809736],"iteration":817,"passed_time":5.127346111,"remaining_time":1.140803169},
{"learn":[0.1574249475],"iteration":818,"passed_time":5.133408782,"remaining_time":1.134489609},
{"learn":[0.1571894915],"iteration":819,"passed_time":5.137976156,"remaining_time":1.127848425},
{"learn":[0.1569229857],"iteration":820,"passed_time":5.144766222,"remaining_time":1.121696899},
{"learn":[0.1567515606],"iteration":821,"passed_time":5.148871151,"remaining_time":1.114962366},
{"learn":[0.1566094641],"iteration":822,"passed_time":5.153213514,"remaining_time":1.108285288},
{"learn":[0.1564800348],"iteration":823,"passed_time":5.159583113,"remaining_time":1.102046879},
{"learn":[0.1562962768],"iteration":824,"passed_time":5.163811351,"remaining_time":1.095353923},
{"learn":[0.1560552337],"iteration":825,"passed_time":5.16831617,"remaining_time":1.088725198},
{"learn":[0.1559560824],"iteration":826,"passed_time":5.174154172,"remaining_time":1.082380498},
{"learn":[0.1559089184],"iteration":827,"passed_time":5.177515075,"remaining_time":1.075522455},
{"learn":[0.1557324442],"iteration":828,"passed_time":5.181854273,"remaining_time":1.068874645},
{"learn":[0.1555458218],"iteration":829,"passed_time":5.186150419,"remaining_time":1.06222358},
{"learn":[0.1553554902],"iteration":830,"passed_time":5.192141255,"remaining_time":1.05592283},
{"learn":[0.1550920603],"iteration":831,"passed_time":5.196524208,"remaining_time":1.049298157},
{"learn":[0.1548630899],"iteration":832,"passed_time":5.201321448,"remaining_time":1.042761923},
{"learn":[0.1545184827],"iteration":833,"passed_time":5.207351538,"remaining_time":1.036475246},
{"learn":[0.1543126636],"iteration":834,"passed_time":5.211702081,"remaining_time":1.029857297},
{"learn":[0.1541227149],"iteration":835,"passed_time":5.21609677,"remaining_time":1.023253433},
{"learn":[0.1539103686],"iteration":836,"passed_time":5.222051942,"remaining_time":1.016958741},
{"learn":[0.1537382061],"iteration":837,"passed_time":5.228303452,"remaining_time":1.010722147},
{"learn":[0.1535403493],"iteration":838,"passed_time":5.232821991,"remaining_time":1.004152969},
{"learn":[0.1533625286],"iteration":839,"passed_time":5.240012075,"remaining_time":0.9980975381},
{"learn":[0.1531820474],"iteration":840,"passed_time":5.244490619,"remaining_time":0.9915267638},
{"learn":[0.1530592427],"iteration":841,"passed_time":5.248898315,"remaining_time":0.9849476648},
{"learn":[0.1527785937],"iteration":842,"passed_time":5.25494634,"remaining_time":0.9786792117},
{"learn":[0.152709335],"iteration":843,"passed_time":5.259996861,"remaining_time":0.9722269079},
{"learn":[0.1524559285],"iteration":844,"passed_time":5.264362419,"remaining_time":0.9656522781},
{"learn":[0.1523783961],"iteration":845,"passed_time":5.269423505,"remaining_time":0.9592094796},
{"learn":[0.1522565029],"iteration":846,"passed_time":5.274349049,"remaining_time":0.9527454599},
{"learn":[0.1521618164],"iteration":847,"passed_time":5.278637509,"remaining_time":0.9461708743},
{"learn":[0.1519376393],"iteration":848,"passed_time":5.282843865,"remaining_time":0.9395870715},
{"learn":[0.1517790949],"iteration":849,"passed_time":5.288845171,"remaining_time":0.9333256184},
{"learn":[0.1516632221],"iteration":850,"passed_time":5.293179612,"remaining_time":0.9267729286},
{"learn":[0.151523678],"iteration":851,"passed_time":5.297358989,"remaining_time":0.9201985099},
{"learn":[0.1514836498],"iteration":852,"passed_time":5.303338053,"remaining_time":0.9139398521},
{"learn":[0.1513292799],"iteration":853,"passed_time":5.307591144,"remaining_time":0.9073867763},
{"learn":[0.1510513804],"iteration":854,"passed_time":5.311796433,"remaining_time":0.900830974},
{"learn":[0.1507388316],"iteration":855,"passed_time":5.318450077,"remaining_time":0.8946925363},
{"learn":[0.1505229369],"iteration":856,"passed_time":5.322693674,"remaining_time":0.8881507531},
{"learn":[0.1502397722],"iteration":857,"passed_time":5.327054008,"remaining_time":0.881633647},
{"learn":[0.1500363854],"iteration":858,"passed_time":5.332875995,"remaining_time":0.8753614846},
{"learn":[0.1498203245],"iteration":859,"passed_time":5.338405041,"remaining_time":0.8690426811},
{"learn":[0.1495943472],"iteration":860,"passed_time":5.34310772,"remaining_time":0.8625923032},
{"learn":[0.1493377351],"iteration":861,"passed_time":5.34762378,"remaining_time":0.8561161041},
{"learn":[0.1490403786],"iteration":862,"passed_time":5.35295495,"remaining_time":0.8497738448},
{"learn":[0.1488487101],"iteration":863,"passed_time":5.357226716,"remaining_time":0.8432671682},
{"learn":[0.1486228038],"iteration":864,"passed_time":5.361413696,"remaining_time":0.8367524265},
{"learn":[0.1483776456],"iteration":865,"passed_time":5.367446323,"remaining_time":0.8305286458},
{"learn":[0.1483079551],"iteration":866,"passed_time":5.371603181,"remaining_time":0.8240175583},
{"learn":[0.1481039444],"iteration":867,"passed_time":5.375852087,"remaining_time":0.8175258934},
{"learn":[0.1478474779],"iteration":868,"passed_time":5.381338215,"remaining_time":0.8112258989},
{"learn":[0.1477632951],"iteration":869,"passed_time":5.386371105,"remaining_time":0.8048600502},
{"learn":[0.1475353818],"iteration":870,"passed_time":5.391955423,"remaining_time":0.7985789318},
{"learn":[0.1472728128],"iteration":871,"passed_time":5.396936868,"remaining_time":0.7922109165},
{"learn":[0.1470105306],"iteration":872,"passed_time":5.401387573,"remaining_time":0.7857688679},
{"learn":[0.1468928072],"iteration":873,"passed_time":5.405719862,"remaining_time":0.7793143051},
{"learn":[0.1466080869],"iteration":874,"passed_time":5.410072685,"remaining_time":0.7728675265},
{"learn":[0.1463289843],"iteration":875,"passed_time":5.416205498,"remaining_time":0.7666774906},
{"learn":[0.1461916323],"iteration":876,"passed_time":5.420430417,"remaining_time":0.7602200014},
{"learn":[0.1461099021],"iteration":877,"passed_time":5.424726263,"remaining_time":0.7537774534},
{"learn":[0.1459986035],"iteration":878,"passed_time":5.43069754,"remaining_time":0.7475704235},
{"learn":[0.1457040578],"iteration":879,"passed_time":5.434958707,"remaining_time":0.7411307327},
{"learn":[0.1453984872],"iteration":880,"passed_time":5.439104485,"remaining_time":0.7346804015},
{"learn":[0.1451172793],"iteration":881,"passed_time":5.444372197,"remaining_time":0.728385396},
{"learn":[0.1449227171],"iteration":882,"passed_time":5.449681938,"remaining_time":0.7220982862},
{"learn":[0.1446564306],"iteration":883,"passed_time":5.45394514,"remaining_time":0.7156760591},
{"learn":[0.1443844782],"iteration":884,"passed_time":5.45792327,"remaining_time":0.7092216678},
{"learn":[0.1442051528],"iteration":885,"passed_time":5.463922171,"remaining_time":0.7030328752},
{"learn":[0.1440510573],"iteration":886,"passed_time":5.467917056,"remaining_time":0.6965892078},
{"learn":[0.1438396293],"iteration":887,"passed_time":5.47208126,"remaining_time":0.6901724112},
{"learn":[0.1436890691],"iteration":888,"passed_time":5.477364581,"remaining_time":0.6839004145},
{"learn":[0.1435485871],"iteration":889,"passed_time":5.481683311,"remaining_time":0.6775114205},
{"learn":[0.1433427336],"iteration":890,"passed_time":5.485983333,"remaining_time":0.6711247849},
{"learn":[0.1430975562],"iteration":891,"passed_time":5.49022,"remaining_time":0.664735157},
{"learn":[0.1429199621],"iteration":892,"passed_time":5.496173868,"remaining_time":0.6585561074},
{"learn":[0.1426557439],"iteration":893,"passed_time":5.500312507,"remaining_time":0.6521623331},
{"learn":[0.1424728206],"iteration":894,"passed_time":5.504546721,"remaining_time":0.6457848109},
{"learn":[0.1422976255],"iteration":895,"passed_time":5.510641221,"remaining_time":0.6396279988},
{"learn":[0.1419663182],"iteration":896,"passed_time":5.514730225,"remaining_time":0.6332410404},
{"learn":[0.1416704718],"iteration":897,"passed_time":5.518791728,"remaining_time":0.626856076},
{"learn":[0.1415373311],"iteration":898,"passed_time":5.524538286,"remaining_time":0.6206655917},
{"learn":[0.1413802754],"iteration":899,"passed_time":5.529581734,"remaining_time":0.6143979704},
{"learn":[0.1412717245],"iteration":900,"passed_time":5.533859643,"remaining_time":0.6080489508},
{"learn":[0.1410256485],"iteration":901,"passed_time":5.537911569,"remaining_time":0.6016799709},
{"learn":[0.1407666489],"iteration":902,"passed_time":5.545125867,"remaining_time":0.5956558241},
{"learn":[0.1405827994],"iteration":903,"passed_time":5.549481447,"remaining_time":0.5893254634},
{"learn":[0.1403941262],"iteration":904,"passed_time":5.553943869,"remaining_time":0.5830106824},
{"learn":[0.1402493442],"iteration":905,"passed_time":5.560109829,"remaining_time":0.5768767372},
{"learn":[0.140131495],"iteration":906,"passed_time":5.564351236,"remaining_time":0.5705453858},
{"learn":[0.1399138725],"iteration":907,"passed_time":5.568532676,"remaining_time":0.5642125619},
{"learn":[0.1398878941],"iteration":908,"passed_time":5.57510274,"remaining_time":0.5581235966},
{"learn":[0.1396527542],"iteration":909,"passed_time":5.580023315,"remaining_time":0.5518704378},
{"learn":[0.1394947784],"iteration":910,"passed_time":5.584105958,"remaining_time":0.5455383428},
{"learn":[0.1392315223],"iteration":911,"passed_time":5.589840854,"remaining_time":0.5393706087},
{"learn":[0.1390852584],"iteration":912,"passed_time":5.594132862,"remaining_time":0.5330663296},
{"learn":[0.1388935162],"iteration":913,"passed_time":5.59837282,"remaining_time":0.5267615564},
{"learn":[0.1386591653],"iteration":914,"passed_time":5.602901086,"remaining_time":0.520488079},
{"learn":[0.1384700445],"iteration":915,"passed_time":5.608419212,"remaining_time":0.5143091854},
{"learn":[0.1383298098],"iteration":916,"passed_time":5.612790541,"remaining_time":0.5080279334},
{"learn":[0.1381512437],"iteration":917,"passed_time":5.617147228,"remaining_time":0.5017495345},
{"learn":[0.1379943269],"iteration":918,"passed_time":5.622936,"remaining_time":0.4956015408},
{"learn":[0.1377137381],"iteration":919,"passed_time":5.627277909,"remaining_time":0.4893285138},
{"learn":[0.1374916554],"iteration":920,"passed_time":5.631360484,"remaining_time":0.4830374356},
{"learn":[0.1373049725],"iteration":921,"passed_time":5.63714785,"remaining_time":0.4768953713},
{"learn":[0.1371164642],"iteration":922,"passed_time":5.641459303,"remaining_time":0.4706309495},
{"learn":[0.1369606077],"iteration":923,"passed_time":5.645700598,"remaining_time":0.4643649842},
{"learn":[0.1368184959],"iteration":924,"passed_time":5.650060937,"remaining_time":0.4581130489},
{"learn":[0.1367354454],"iteration":925,"passed_time":5.656801612,"remaining_time":0.4520554204},
{"learn":[0.1366947647],"iteration":926,"passed_time":5.661474154,"remaining_time":0.4458334555},
{"learn":[0.1365188487],"iteration":927,"passed_time":5.665560516,"remaining_time":0.4395693504},
{"learn":[0.1362964198],"iteration":928,"passed_time":5.671636369,"remaining_time":0.433461983},
{"learn":[0.1361816787],"iteration":929,"passed_time":5.675842335,"remaining_time":0.4272139392},
{"learn":[0.1360336834],"iteration":930,"passed_time":5.680267256,"remaining_time":0.4209865098},
{"learn":[0.1358284578],"iteration":931,"passed_time":5.686267571,"remaining_time":0.4148778914},
{"learn":[0.1356911334],"iteration":932,"passed_time":5.690725804,"remaining_time":0.4086587662},
{"learn":[0.1356288107],"iteration":933,"passed_time":5.694908791,"remaining_time":0.4024239617},
{"learn":[0.1355256443],"iteration":934,"passed_time":5.700475117,"remaining_time":0.3962897141},
{"learn":[0.1353732458],"iteration":935,"passed_time":5.704892051,"remaining_time":0.3900780889},
{"learn":[0.1352823339],"iteration":936,"passed_time":5.708933554,"remaining_time":0.3838450522},
{"learn":[0.1350696346],"iteration":937,"passed_time":5.713035895,"remaining_time":0.3776207095},
{"learn":[0.1348681874],"iteration":938,"passed_time":5.718940591,"remaining_time":0.3715179724},
{"learn":[0.1345985058],"iteration":939,"passed_time":5.723115407,"remaining_time":0.3653052387},
{"learn":[0.1344950505],"iteration":940,"passed_time":5.727381511,"remaining_time":0.3591025602},
{"learn":[0.1343224447],"iteration":941,"passed_time":5.733435277,"remaining_time":0.3530140617},
{"learn":[0.13416563],"iteration":942,"passed_time":5.737682258,"remaining_time":0.3468164249},
{"learn":[0.134010461],"iteration":943,"passed_time":5.74204335,"remaining_time":0.3406296902},
{"learn":[0.1338774409],"iteration":944,"passed_time":5.746392827,"remaining_time":0.3344461434},
{"learn":[0.133703633],"iteration":945,"passed_time":5.752649592,"remaining_time":0.3283753467},
{"learn":[0.1335207311],"iteration":946,"passed_time":5.757087946,"remaining_time":0.3222023877},
{"learn":[0.1333455601],"iteration":947,"passed_time":5.761226993,"remaining_time":0.3160166705},
{"learn":[0.1331822721],"iteration":948,"passed_time":5.767246839,"remaining_time":0.3099363422},
{"learn":[0.1329512695],"iteration":949,"passed_time":5.773077414,"remaining_time":0.3038461797},
{"learn":[0.1328558404],"iteration":950,"passed_time":5.777848384,"remaining_time":0.2977019672},
{"learn":[0.1326762282],"iteration":951,"passed_time":5.783203551,"remaining_time":0.291590095},
{"learn":[0.1325055099],"iteration":952,"passed_time":5.787322101,"remaining_time":0.2854188235},
{"learn":[0.1322400344],"iteration":953,"passed_time":5.791591336,"remaining_time":0.279259121},
{"learn":[0.132112266],"iteration":954,"passed_time":5.797943566,"remaining_time":0.2732015293},
{"learn":[0.1319823402],"iteration":955,"passed_time":5.802129222,"remaining_time":0.2670436043},
{"learn":[0.1317545454],"iteration":956,"passed_time":5.806579001,"remaining_time":0.2609016688},
{"learn":[0.1315432879],"iteration":957,"passed_time":5.812138653,"remaining_time":0.2548119242},
{"learn":[0.1313154264],"iteration":958,"passed_time":5.816597458,"remaining_time":0.2486762208},
{"learn":[0.1310570556],"iteration":959,"passed_time":5.820774828,"remaining_time":0.2425322845},
{"learn":[0.1309509624],"iteration":960,"passed_time":5.824955189,"remaining_time":0.2363925623},
{"learn":[0.1307710466],"iteration":961,"passed_time":5.831068727,"remaining_time":0.2303332761},
{"learn":[0.1306343802],"iteration":962,"passed_time":5.835241907,"remaining_time":0.2241993256},
{"learn":[0.1304932423],"iteration":963,"passed_time":5.839205672,"remaining_time":0.2180616226},
{"learn":[0.130335939],"iteration":964,"passed_time":5.845236391,"remaining_time":0.2120033924},
{"learn":[0.1302285531],"iteration":965,"passed_time":5.850534371,"remaining_time":0.2059194292},
{"learn":[0.1299027793],"iteration":966,"passed_time":5.854706938,"remaining_time":0.1997986856},
{"learn":[0.12984532],"iteration":967,"passed_time":5.860578959,"remaining_time":0.1937381474},
{"learn":[0.1297115377],"iteration":968,"passed_time":5.865008807,"remaining_time":0.1876318607},
{"learn":[0.1294667415],"iteration":969,"passed_time":5.869229319,"remaining_time":0.1815225563},
{"learn":[0.1292576738],"iteration":970,"passed_time":5.873707354,"remaining_time":0.1754248334},
{"learn":[0.1290941015],"iteration":971,"passed_time":5.878758246,"remaining_time":0.1693469454},
{"learn":[0.128891624],"iteration":972,"passed_time":5.882909438,"remaining_time":0.1632462023},
{"learn":[0.1287532903],"iteration":973,"passed_time":5.887013697,"remaining_time":0.1571482096},
{"learn":[0.1286014123],"iteration":974,"passed_time":5.892947977,"remaining_time":0.1511012302},
{"learn":[0.1284176335],"iteration":975,"passed_time":5.897367181,"remaining_time":0.1450172258},
{"learn":[0.1283422129],"iteration":976,"passed_time":5.901696304,"remaining_time":0.1389345087},
{"learn":[0.1282174396],"iteration":977,"passed_time":5.906628302,"remaining_time":0.1328689393},
{"learn":[0.1280235403],"iteration":978,"passed_time":5.912243635,"remaining_time":0.1268203436},
{"learn":[0.1279311326],"iteration":979,"passed_time":5.91656199,"remaining_time":0.1207461631},
{"learn":[0.127761385],"iteration":980,"passed_time":5.920910133,"remaining_time":0.1146761392},
{"learn":[0.1276021136],"iteration":981,"passed_time":5.926936387,"remaining_time":0.1086403818},
{"learn":[0.127404477],"iteration":982,"passed_time":5.931151341,"remaining_time":0.1025733192},
{"learn":[0.1272458191],"iteration":983,"passed_time":5.935460334,"remaining_time":0.09651155015},
{"learn":[0.1270909955],"iteration":984,"passed_time":5.942437138,"remaining_time":0.09049396656},
{"learn":[0.1269218064],"iteration":985,"passed_time":5.947758688,"remaining_time":0.08445093472},
{"learn":[0.126749189],"iteration":986,"passed_time":5.952052063,"remaining_time":0.07839582251},
{"learn":[0.1265152189],"iteration":987,"passed_time":5.958355508,"remaining_time":0.07236869038},
{"learn":[0.1263331147],"iteration":988,"passed_time":5.962687829,"remaining_time":0.06631907596},
{"learn":[0.1261380152],"iteration":989,"passed_time":5.96708265,"remaining_time":0.06027356212},
{"learn":[0.1259265186],"iteration":990,"passed_time":5.972828958,"remaining_time":0.0542436535},
{"learn":[0.1256785129],"iteration":991,"passed_time":5.977231155,"remaining_time":0.04820347706},
{"learn":[0.1254657936],"iteration":992,"passed_time":5.981580096,"remaining_time":0.04216622424},
{"learn":[0.1253301433],"iteration":993,"passed_time":5.987364633,"remaining_time":0.036141034},
{"learn":[0.1251683664],"iteration":994,"passed_time":5.99167953,"remaining_time":0.03010894236},
{"learn":[0.1249911309],"iteration":995,"passed_time":5.995889983,"remaining_time":0.02407987945},
{"learn":[0.1246767525],"iteration":996,"passed_time":6.00009567,"remaining_time":0.01805445036},
{"learn":[0.1244491579],"iteration":997,"passed_time":6.006243562,"remaining_time":0.01203656024},
{"learn":[0.1242775314],"iteration":998,"passed_time":6.010645899,"remaining_time":0.006016662562},
{"learn":[0.1240815532],"iteration":999,"passed_time":6.014914465,"remaining_time":0}
]}